[{"subject": "ACCC111E", "number": 0, "Mo": [], "Tu": [], "We": [], "Th": [], "Fr": [{"Time": "07:30", "Venue": "V11-G02"}]}, {"subject": "ACCC111a", "number": 1, "Mo": [], "Tu": [{"Time": "13:00", "Venue": "V04-G03"}], "We": [], "Th": [{"Time": "07:30", "Venue": "V04-G03"}, {"Time": "09:30", "Venue": "V04-G03"}], "Fr": [{"Time": "07:30", "Venue": "V04-G03"}]}, {"subject": "ACCC271", "number": 2, "Mo": [{"Time": "11:00", "Venue": "V9C-G02"}, {"Time": "13:00", "Venue": "V9C-G02"}], "Tu": [], "We": [{"Time": "09:30", "Venue": "V9C-G02"}], "Th": [], "Fr": [{"Time": "11:00", "Venue": "V9C-G02"}]}, {"subject": "ACCC371", "number": 3, "Mo": [], "Tu": [], "We": [{"Time": "09:30", "Venue": "V04-K03"}, {"Time": "11:00", "Venue": "V04-K03"}], "Th": [], "Fr": [{"Time": "07:30", "Venue": "V04-K03"}, {"Time": "09:30", "Venue": "V04-K03"}]}, {"subject": "ACCD411", "number": 4, "Mo": [{"Time": "07:30", "Venue": "V9B-G01"}], "Tu": [], "We": [], "Th": [{"Time": "14:30", "Venue": "V9B-G01"}], "Fr": []}, {"subject": "ACCD512", "number": 5, "Mo": [], "Tu": [], "We": [{"Time": "11:00", "Venue": "V06-G07"}], "Th": [], "Fr": []}, {"subject": "ACCE112", "number": 6, "Mo": [{"Time": "14:30", "Venue": "V12-G01"}], "Tu": [], "We": [], "Th": [{"Time": "07:30", "Venue": "V12-G01"}], "Fr": []}, {"subject": "ACCE212", "number": 7, "Mo": [], "Tu": [], "We": [{"Time": "09:30", "Venue": "V25-G08"}], "Th": [], "Fr": []}, {"subject": "ACCE312", "number": 8, "Mo": [], "Tu": [{"Time": "16:00", "Venue": "V9A-G09"}], "We": [], "Th": [{"Time": "09:30", "Venue": "V9A-G09"}], "Fr": []}, {"subject": "ACCE412", "number": 9, "Mo": [], "Tu": [], "We": [{"Time": "13:00", "Venue": "V9A-G13"}], "Th": [{"Time": "13:00", "Venue": "V9A-G13"}], "Fr": []}, {"subject": "ACCF111E", "number": 10, "Mo": [{"Time": "13:00", "Venue": "V12-G05"}, {"Time": "14:30", "Venue": "V12-G05"}], "Tu": [], "We": [{"Time": "13:00", "Venue": "V12-G05"}], "Th": [{"Time": "07:30", "Venue": "V12-G05"}], "Fr": []}, {"subject": "ACCF111a", "number": 11, "Mo": [], "Tu": [], "We": [], "Th": [], "Fr": [{"Time": "07:30", "Venue": "V12-G04"}]}, {"subject": "ACCF211", "number": 12, "Mo": [], "Tu": [], "We": [], "Th": [{"Time": "09:30", "Venue": "V12-G05"}], "Fr": [{"Time": "13:00", "Venue": "V12-G05"}]}, {"subject": "ACCF371", "number": 13, "Mo": [{"Time": "14:30", "Venue": "V12-G02"}], "Tu": [], "We": [{"Time": "11:00", "Venue": "V12-G02"}, {"Time": "13:00", "Venue": "V12-G02"}], "Th": [{"Time": "07:30", "Venue": "V12-G02"}], "Fr": []}, {"subject": "ACCG211", "number": 14, "Mo": [], "Tu": [], "We": [], "Th": [{"Time": "11:00", "Venue": "V25-G03"}], "Fr": []}, {"subject": "ACCS111E", "number": 15, "Mo": [{"Time": "14:30", "Venue": "V06-G02"}], "Tu": [], "We": [], "Th": [{"Time": "07:30", "Venue": "V06-G02"}], "Fr": []}, {"subject": "ACCS111a", "number": 16, "Mo": [], "Tu": [], "We": [], "Th": [{"Time": "07:30", "Venue": "V04-K03"}], "Fr": [{"Time": "13:00", "Venue": "V04-K03"}]}, {"subject": "ACFS111", "number": 17, "Mo": [{"Time": "07:30", "Venue": "V12-G05"}], "Tu": [{"Time": "13:00", "Venue": "V12-G05"}], "We": [], "Th": [{"Time": "14:30", "Venue": "V12-G05"}, {"Time": "16:00", "Venue": "V12-G05"}], "Fr": []}, {"subject": "ACFS112", "number": 18, "Mo": [{"Time": "13:00", "Venue": "V04-G03"}], "Tu": [{"Time": "09:30", "Venue": "V04-G03"}], "We": [], "Th": [{"Time": "13:00", "Venue": "V04-G03"}], "Fr": [{"Time": "11:00", "Venue": "V04-G03"}]}, {"subject": "ACMP311B", "number": 19, "Mo": [], "Tu": [{"Time": "13:00", "Venue": "V9A-106"}], "We": [], "Th": [{"Time": "16:00", "Venue": "V9A-106"}], "Fr": []}, {"subject": "ACMP311E", "number": 20, "Mo": [], "Tu": [{"Time": "07:30", "Venue": "V9A-106"}], "We": [], "Th": [{"Time": "13:00", "Venue": "V9A-106"}], "Fr": []}, {"subject": "ACMP311U", "number": 21, "Mo": [], "Tu": [{"Time": "11:00", "Venue": "V9A-106"}], "We": [], "Th": [{"Time": "09:30", "Venue": "V9A-106"}], "Fr": []}, {"subject": "AFAF211", "number": 22, "Mo": [], "Tu": [{"Time": "11:00", "Venue": "V06-G06"}], "We": [], "Th": [], "Fr": []}, {"subject": "AFAF311", "number": 23, "Mo": [], "Tu": [], "We": [], "Th": [], "Fr": [{"Time": "11:00", "Venue": "V06-G09"}]}, {"subject": "AFAF411", "number": 24, "Mo": [], "Tu": [], "We": [{"Time": "14:30", "Venue": "V06-G09"}], "Th": [], "Fr": []}, {"subject": "AFIP211", "number": 25, "Mo": [], "Tu": [], "We": [], "Th": [], "Fr": [{"Time": "07:30", "Venue": "V07-K01"}]}, {"subject": "AFIP311", "number": 26, "Mo": [], "Tu": [{"Time": "07:30", "Venue": "V06-G06"}], "We": [], "Th": [], "Fr": []}, {"subject": "AFIP411", "number": 27, "Mo": [], "Tu": [], "We": [], "Th": [{"Time": "13:00", "Venue": "V06-G09"}], "Fr": []}, {"subject": "AFLL111", "number": 28, "Mo": [], "Tu": [], "We": [{"Time": "11:00", "Venue": "V31-G02"}], "Th": [], "Fr": []}, {"subject": "AFLL211", "number": 29, "Mo": [], "Tu": [], "We": [], "Th": [{"Time": "09:30", "Venue": "V07-206"}], "Fr": []}, {"subject": "AFLL311", "number": 30, "Mo": [], "Tu": [], "We": [], "Th": [], "Fr": [{"Time": "07:30", "Venue": "V25-G08"}]}, {"subject": "AFPR111", "number": 31, "Mo": [], "Tu": [], "We": [{"Time": "14:30", "Venue": "V07-206"}], "Th": [], "Fr": [{"Time": "11:00", "Venue": "V07-206"}]}, {"subject": "AFRD512", "number": 32, "Mo": [], "Tu": [], "We": [], "Th": [], "Fr": [{"Time": "16:00", "Venue": "V06-G08"}]}, {"subject": "AFRE112", "number": 33, "Mo": [], "Tu": [], "We": [], "Th": [], "Fr": [{"Time": "11:00", "Venue": "V12-G06"}]}, {"subject": "AFRE212", "number": 34, "Mo": [], "Tu": [{"Time": "13:00", "Venue": "V06-G08"}], "We": [], "Th": [{"Time": "16:00", "Venue": "V06-G08"}], "Fr": []}, {"subject": "AFRE312", "number": 35, "Mo": [], "Tu": [{"Time": "09:30", "Venue": "V06-G08"}], "We": [{"Time": "11:00", "Venue": "V06-G08"}], "Th": [], "Fr": []}, {"subject": "AFRE412", "number": 36, "Mo": [], "Tu": [], "We": [], "Th": [{"Time": "07:30", "Venue": "V9A-G07"}], "Fr": []}, {"subject": "AFRF111", "number": 37, "Mo": [], "Tu": [], "We": [{"Time": "13:00", "Venue": "V25-G07"}], "Th": [], "Fr": []}, {"subject": "AFRF211", "number": 38, "Mo": [], "Tu": [], "We": [], "Th": [], "Fr": [{"Time": "13:00", "Venue": "V9A-G13"}]}, {"subject": "AFRF311", "number": 39, "Mo": [], "Tu": [], "We": [{"Time": "07:30", "Venue": "V25-G07"}], "Th": [], "Fr": [{"Time": "09:30", "Venue": "V25-G07"}]}, {"subject": "AFRF411", "number": 40, "Mo": [], "Tu": [], "We": [{"Time": "09:30", "Venue": "V06-G08"}], "Th": [], "Fr": []}, {"subject": "AFRI111a", "number": 41, "Mo": [], "Tu": [], "We": [], "Th": [], "Fr": [{"Time": "11:00", "Venue": "V12-G06"}]}, {"subject": "AFRI211", "number": 42, "Mo": [], "Tu": [{"Time": "11:00", "Venue": "V06-G07"}], "We": [], "Th": [], "Fr": [{"Time": "14:30", "Venue": "V06-G07"}]}, {"subject": "AFRI311", "number": 43, "Mo": [], "Tu": [{"Time": "14:30", "Venue": "V12-G03"}], "We": [], "Th": [], "Fr": [{"Time": "07:30", "Venue": "V12-G03"}]}, {"subject": "AFRI411", "number": 44, "Mo": [], "Tu": [], "We": [], "Th": [], "Fr": [{"Time": "07:30", "Venue": "Dept-7"}]}, {"subject": "ALDA111a", "number": 45, "Mo": [{"Time": "13:00", "Venue": "V25-G06"}], "Tu": [], "We": [], "Th": [], "Fr": []}, {"subject": "ALDA111b", "number": 46, "Mo": [{"Time": "11:00", "Venue": "V11-G02"}], "Tu": [], "We": [], "Th": [], "Fr": []}, {"subject": "ALDE111A", "number": 47, "Mo": [{"Time": "07:30", "Venue": "V9A-G13"}], "Tu": [], "We": [], "Th": [], "Fr": []}, {"subject": "ALDE111B", "number": 48, "Mo": [], "Tu": [], "We": [], "Th": [{"Time": "14:30", "Venue": "V11-G02"}], "Fr": []}, {"subject": "ALDE111C", "number": 49, "Mo": [], "Tu": [{"Time": "16:00", "Venue": "V07-110"}], "We": [], "Th": [], "Fr": []}, {"subject": "ALDE111D", "number": 50, "Mo": [], "Tu": [], "We": [{"Time": "11:00", "Venue": "V9B-G02"}], "Th": [], "Fr": []}, {"subject": "ALDE111E", "number": 51, "Mo": [], "Tu": [], "We": [{"Time": "11:00", "Venue": "V07-110"}], "Th": [], "Fr": []}, {"subject": "ALDE111F", "number": 52, "Mo": [], "Tu": [], "We": [{"Time": "16:00", "Venue": "V07-G04"}], "Th": [], "Fr": []}, {"subject": "ALDE111G", "number": 53, "Mo": [], "Tu": [{"Time": "07:30", "Venue": "V06-111"}], "We": [], "Th": [], "Fr": []}, {"subject": "ALDE111H", "number": 54, "Mo": [], "Tu": [{"Time": "14:30", "Venue": "V12-G01"}], "We": [], "Th": [], "Fr": []}, {"subject": "ALDE111I", "number": 55, "Mo": [], "Tu": [], "We": [], "Th": [{"Time": "11:00", "Venue": "V9B-G01"}], "Fr": []}, {"subject": "ALDE111J", "number": 56, "Mo": [], "Tu": [], "We": [], "Th": [{"Time": "11:00", "Venue": "V06-111"}], "Fr": []}, {"subject": "ALDE111K", "number": 57, "Mo": [{"Time": "16:00", "Venue": "V25-G07"}], "Tu": [], "We": [], "Th": [], "Fr": []}, {"subject": "ALDE111L", "number": 58, "Mo": [], "Tu": [], "We": [], "Th": [{"Time": "09:30", "Venue": "V06-G07"}], "Fr": []}, {"subject": "ALDE111M", "number": 59, "Mo": [], "Tu": [], "We": [], "Th": [{"Time": "13:00", "Venue": "V07-G04"}], "Fr": []}, {"subject": "ALDE111N", "number": 60, "Mo": [], "Tu": [], "We": [], "Th": [{"Time": "13:00", "Venue": "V9B-G02"}], "Fr": []}, {"subject": "ALDE111O", "number": 61, "Mo": [], "Tu": [], "We": [], "Th": [], "Fr": [{"Time": "11:00", "Venue": "V9B-G01"}]}, {"subject": "ALDE111P", "number": 62, "Mo": [], "Tu": [], "We": [], "Th": [{"Time": "13:00", "Venue": "V9C-G01"}], "Fr": []}, {"subject": "ALDE111Q", "number": 63, "Mo": [{"Time": "16:00", "Venue": "V9C-G01"}], "Tu": [], "We": [], "Th": [], "Fr": []}, {"subject": "ALDE111R", "number": 64, "Mo": [{"Time": "11:00", "Venue": "V06-G02"}], "Tu": [], "We": [], "Th": [], "Fr": []}, {"subject": "ALDE111S", "number": 65, "Mo": [], "Tu": [{"Time": "13:00", "Venue": "V25-G07"}], "We": [], "Th": [], "Fr": []}, {"subject": "ALDE111T", "number": 66, "Mo": [], "Tu": [{"Time": "13:00", "Venue": "V07-110"}], "We": [], "Th": [], "Fr": []}, {"subject": "ALDE111U", "number": 67, "Mo": [], "Tu": [{"Time": "16:00", "Venue": "V11-G02"}], "We": [], "Th": [], "Fr": []}, {"subject": "ALDE111V", "number": 68, "Mo": [], "Tu": [], "We": [], "Th": [{"Time": "16:00", "Venue": "V9A-G09"}], "Fr": []}, {"subject": "ALDE111W", "number": 69, "Mo": [], "Tu": [], "We": [], "Th": [], "Fr": [{"Time": "16:00", "Venue": "V25-G07"}]}, {"subject": "ALDE111X", "number": 70, "Mo": [{"Time": "13:00", "Venue": "V9A-G07"}], "Tu": [], "We": [], "Th": [], "Fr": []}, {"subject": "ALDE111Z", "number": 71, "Mo": [], "Tu": [], "We": [{"Time": "09:30", "Venue": "V11-G02"}], "Th": [], "Fr": []}, {"subject": "ALDE111b", "number": 72, "Mo": [], "Tu": [], "We": [], "Th": [{"Time": "11:00", "Venue": "V07-K01"}], "Fr": []}, {"subject": "ANAV112", "number": 73, "Mo": [], "Tu": [], "We": [], "Th": [], "Fr": [{"Time": "09:30", "Venue": "Dept-3"}]}, {"subject": "AUDF211", "number": 74, "Mo": [], "Tu": [{"Time": "13:00", "Venue": "V06-G02"}], "We": [{"Time": "11:00", "Venue": "V06-G02"}], "Th": [], "Fr": []}, {"subject": "AUDF371", "number": 75, "Mo": [], "Tu": [], "We": [], "Th": [{"Time": "11:00", "Venue": "V12-G06"}], "Fr": []}, {"subject": "AUDT271", "number": 76, "Mo": [], "Tu": [{"Time": "07:30", "Venue": "V9C-G02"}], "We": [], "Th": [{"Time": "09:30", "Venue": "V9C-G02"}], "Fr": []}, {"subject": "AUDT371", "number": 77, "Mo": [{"Time": "11:00", "Venue": "V04-K03"}], "Tu": [], "We": [{"Time": "13:00", "Venue": "V04-K03"}], "Th": [], "Fr": []}, {"subject": "BMAN111E", "number": 78, "Mo": [], "Tu": [], "We": [{"Time": "07:30", "Venue": "V25-G01"}], "Th": [], "Fr": []}, {"subject": "BMAN111U", "number": 79, "Mo": [], "Tu": [{"Time": "07:30", "Venue": "V12-G02"}], "We": [], "Th": [], "Fr": []}, {"subject": "BMAN111V", "number": 80, "Mo": [], "Tu": [], "We": [], "Th": [{"Time": "11:00", "Venue": "V12-G02"}], "Fr": []}, {"subject": "BMAN111Y", "number": 81, "Mo": [], "Tu": [{"Time": "16:00", "Venue": "V12-G05"}], "We": [], "Th": [], "Fr": []}, {"subject": "BMAN111a", "number": 82, "Mo": [], "Tu": [{"Time": "07:30", "Venue": "V9B-G02"}], "We": [], "Th": [], "Fr": []}, {"subject": "BMAN213", "number": 83, "Mo": [], "Tu": [], "We": [], "Th": [{"Time": "11:00", "Venue": "V9C-G01"}], "Fr": []}, {"subject": "BMAN214", "number": 84, "Mo": [], "Tu": [], "We": [{"Time": "09:30", "Venue": "V12-G06"}], "Th": [{"Time": "07:30", "Venue": "V12-G06"}], "Fr": []}, {"subject": "BMAN311", "number": 85, "Mo": [], "Tu": [], "We": [], "Th": [{"Time": "13:00", "Venue": "V25-G08"}], "Fr": []}, {"subject": "BMAN312", "number": 86, "Mo": [{"Time": "07:30", "Venue": "V9A-G09"}], "Tu": [], "We": [], "Th": [{"Time": "14:30", "Venue": "V9A-G09"}], "Fr": []}, {"subject": "BMAR211", "number": 87, "Mo": [], "Tu": [{"Time": "14:30", "Venue": "V12-G02"}], "We": [], "Th": [], "Fr": []}, {"subject": "BMAR213", "number": 88, "Mo": [], "Tu": [], "We": [{"Time": "16:00", "Venue": "V12-G02"}], "Th": [], "Fr": []}, {"subject": "BMAR311", "number": 89, "Mo": [], "Tu": [{"Time": "14:30", "Venue": "V25-G06"}], "We": [], "Th": [], "Fr": [{"Time": "07:30", "Venue": "V25-G06"}]}, {"subject": "BMAR312", "number": 90, "Mo": [], "Tu": [{"Time": "07:30", "Venue": "V9C-G01"}], "We": [], "Th": [], "Fr": [{"Time": "13:00", "Venue": "V9C-G01"}]}, {"subject": "BMAR314", "number": 91, "Mo": [{"Time": "09:30", "Venue": "V9B-G01"}], "Tu": [], "We": [{"Time": "16:00", "Venue": "V9B-G01"}], "Th": [], "Fr": []}, {"subject": "BMAR315", "number": 92, "Mo": [], "Tu": [{"Time": "09:30", "Venue": "V25-G09"}], "We": [{"Time": "11:00", "Venue": "V25-G09"}], "Th": [], "Fr": []}, {"subject": "BMAR316", "number": 93, "Mo": [{"Time": "16:00", "Venue": "V06-G02"}], "Tu": [], "We": [{"Time": "13:00", "Venue": "V06-G02"}], "Th": [], "Fr": []}, {"subject": "BSMN211", "number": 94, "Mo": [], "Tu": [], "We": [], "Th": [{"Time": "11:00", "Venue": "V25-G09"}], "Fr": []}, {"subject": "BSMN212", "number": 95, "Mo": [], "Tu": [], "We": [{"Time": "07:30", "Venue": "V9A-103"}], "Th": [], "Fr": [{"Time": "09:30", "Venue": "V9A-103"}]}, {"subject": "BSTD411", "number": 96, "Mo": [], "Tu": [{"Time": "13:00", "Venue": "V9A-G07"}], "We": [], "Th": [{"Time": "16:00", "Venue": "V9A-G07"}], "Fr": []}, {"subject": "BSTD512", "number": 97, "Mo": [{"Time": "16:00", "Venue": "V11-G02"}], "Tu": [], "We": [], "Th": [], "Fr": []}, {"subject": "BSTE112", "number": 98, "Mo": [], "Tu": [{"Time": "14:30", "Venue": "V25-G09"}], "We": [], "Th": [], "Fr": [{"Time": "07:30", "Venue": "V25-G09"}]}, {"subject": "BSTE212", "number": 99, "Mo": [], "Tu": [], "We": [{"Time": "14:30", "Venue": "V9B-G01"}], "Th": [], "Fr": []}, {"subject": "BSTE312", "number": 100, "Mo": [], "Tu": [], "We": [{"Time": "07:30", "Venue": "V25-G03"}], "Th": [], "Fr": [{"Time": "09:30", "Venue": "V25-G03"}]}, {"subject": "BSTE412", "number": 101, "Mo": [], "Tu": [{"Time": "16:00", "Venue": "V9B-G01"}], "We": [], "Th": [{"Time": "09:30", "Venue": "V9B-G01"}], "Fr": []}, {"subject": "BSTG111", "number": 102, "Mo": [], "Tu": [], "We": [{"Time": "07:30", "Venue": "V9B-G01"}], "Th": [], "Fr": []}, {"subject": "BSWG111", "number": 103, "Mo": [], "Tu": [{"Time": "07:30", "Venue": "V9B-G01"}], "We": [], "Th": [], "Fr": [{"Time": "13:00", "Venue": "V9B-G01"}]}, {"subject": "BSWG114", "number": 104, "Mo": [], "Tu": [{"Time": "13:00", "Venue": "V07-206"}], "We": [], "Th": [{"Time": "16:00", "Venue": "V07-206"}], "Fr": []}, {"subject": "BSWG214", "number": 105, "Mo": [{"Time": "11:00", "Venue": "V07-K01"}], "Tu": [], "We": [{"Time": "09:30", "Venue": "V07-K01"}], "Th": [], "Fr": []}, {"subject": "BSWG311", "number": 106, "Mo": [], "Tu": [], "We": [], "Th": [], "Fr": [{"Time": "07:30", "Venue": "V9A-G20"}]}, {"subject": "BSWG412", "number": 107, "Mo": [], "Tu": [{"Time": "13:00", "Venue": "V9B-G02"}], "We": [], "Th": [{"Time": "16:00", "Venue": "V9B-G02"}], "Fr": []}, {"subject": "BSWG414", "number": 108, "Mo": [{"Time": "07:30", "Venue": "V06-111"}], "Tu": [], "We": [], "Th": [{"Time": "14:30", "Venue": "V06-111"}], "Fr": []}, {"subject": "BSWG416", "number": 109, "Mo": [{"Time": "09:30", "Venue": "V06-111"}], "Tu": [], "We": [{"Time": "16:00", "Venue": "V06-111"}], "Th": [], "Fr": []}, {"subject": "BSWG418", "number": 110, "Mo": [], "Tu": [], "We": [], "Th": [], "Fr": [{"Time": "11:00", "Venue": "V25-G09"}]}, {"subject": "BSWG419", "number": 111, "Mo": [], "Tu": [{"Time": "07:30", "Venue": "V07-G04"}], "We": [], "Th": [], "Fr": [{"Time": "13:00", "Venue": "V07-G04"}]}, {"subject": "BSWI111", "number": 112, "Mo": [], "Tu": [], "We": [], "Th": [], "Fr": [{"Time": "07:30", "Venue": "V9A-G07"}]}, {"subject": "BSWI211", "number": 113, "Mo": [{"Time": "16:00", "Venue": "V06-G06"}], "Tu": [], "We": [{"Time": "13:00", "Venue": "V06-G06"}], "Th": [], "Fr": []}, {"subject": "BSWI212", "number": 114, "Mo": [], "Tu": [], "We": [{"Time": "14:30", "Venue": "V25-G07"}], "Th": [], "Fr": [{"Time": "11:00", "Venue": "V25-G07"}]}, {"subject": "BSWI311", "number": 115, "Mo": [{"Time": "16:00", "Venue": "V07-G04"}], "Tu": [], "We": [{"Time": "13:00", "Venue": "V07-G04"}], "Th": [], "Fr": []}, {"subject": "BSWI312", "number": 116, "Mo": [], "Tu": [], "We": [{"Time": "09:30", "Venue": "V25-G09"}], "Th": [], "Fr": []}, {"subject": "BSWI313", "number": 117, "Mo": [], "Tu": [], "We": [], "Th": [], "Fr": [{"Time": "16:00", "Venue": "V07-G04"}]}, {"subject": "BSWI411", "number": 118, "Mo": [], "Tu": [{"Time": "11:00", "Venue": "V07-110"}], "We": [], "Th": [], "Fr": []}, {"subject": "BSWI471E", "number": 119, "Mo": [{"Time": "14:30", "Venue": "V06-G08"}, {"Time": "16:00", "Venue": "V06-G08"}], "Tu": [], "We": [{"Time": "13:00", "Venue": "V06-G08"}], "Th": [{"Time": "07:30", "Venue": "V06-G08"}], "Fr": []}, {"subject": "BSWP471", "number": 120, "Mo": [{"Time": "11:00", "Venue": "V06-G10"}], "Tu": [], "We": [{"Time": "07:30", "Venue": "V06-G10"}, {"Time": "09:30", "Venue": "V06-G10"}], "Th": [], "Fr": [{"Time": "09:30", "Venue": "V06-G10"}]}, {"subject": "BWIA111", "number": 121, "Mo": [], "Tu": [], "We": [{"Time": "07:30", "Venue": "V9A-102"}], "Th": [], "Fr": [{"Time": "09:30", "Venue": "V9A-102"}]}, {"subject": "BWIA273", "number": 122, "Mo": [], "Tu": [{"Time": "14:30", "Venue": "V9A-103"}, {"Time": "16:00", "Venue": "V9A-103"}], "We": [], "Th": [{"Time": "11:00", "Venue": "V9A-103"}], "Fr": [{"Time": "07:30", "Venue": "V9A-103"}]}, {"subject": "BWIA313", "number": 123, "Mo": [{"Time": "13:00", "Venue": "V07-G04"}], "Tu": [], "We": [{"Time": "14:30", "Venue": "V07-G04"}], "Th": [{"Time": "11:00", "Venue": "V07-G04"}], "Fr": [{"Time": "11:00", "Venue": "V07-G04"}]}, {"subject": "BYBV113E", "number": 124, "Mo": [{"Time": "09:30", "Venue": "V9B-G02"}], "Tu": [], "We": [{"Time": "16:00", "Venue": "V9B-G02"}], "Th": [], "Fr": []}, {"subject": "BYBV113a", "number": 125, "Mo": [], "Tu": [], "We": [], "Th": [], "Fr": [{"Time": "14:30", "Venue": "V12-G03"}]}, {"subject": "BYBV211", "number": 126, "Mo": [], "Tu": [{"Time": "14:30", "Venue": "V06-111"}], "We": [], "Th": [], "Fr": [{"Time": "07:30", "Venue": "V06-111"}]}, {"subject": "BYBV312", "number": 127, "Mo": [], "Tu": [], "We": [{"Time": "14:30", "Venue": "V06-G06"}], "Th": [], "Fr": [{"Time": "11:00", "Venue": "V06-G06"}]}, {"subject": "CATD411", "number": 128, "Mo": [], "Tu": [{"Time": "13:00", "Venue": "V11-G01"}], "We": [], "Th": [{"Time": "16:00", "Venue": "V11-G01"}], "Fr": []}, {"subject": "CATD512", "number": 129, "Mo": [], "Tu": [{"Time": "11:00", "Venue": "V11-G01"}], "We": [], "Th": [], "Fr": [{"Time": "14:30", "Venue": "V11-G01"}]}, {"subject": "CATE112", "number": 130, "Mo": [{"Time": "14:30", "Venue": "V11-G01"}, {"Time": "16:00", "Venue": "V11-G01"}], "Tu": [], "We": [], "Th": [{"Time": "07:30", "Venue": "V11-G01"}], "Fr": []}, {"subject": "CATE212", "number": 131, "Mo": [{"Time": "11:00", "Venue": "V11-G01"}], "Tu": [], "We": [{"Time": "07:30", "Venue": "V11-G01"}, {"Time": "09:30", "Venue": "V11-G01"}], "Th": [], "Fr": []}, {"subject": "CATE312", "number": 132, "Mo": [], "Tu": [], "We": [], "Th": [{"Time": "07:30", "Venue": "V9A-G20"}], "Fr": []}, {"subject": "CATE412", "number": 133, "Mo": [], "Tu": [], "We": [], "Th": [], "Fr": [{"Time": "09:30", "Venue": "V11-G01"}]}, {"subject": "CMPF511", "number": 134, "Mo": [], "Tu": [{"Time": "07:30", "Venue": "V11-G01"}], "We": [], "Th": [], "Fr": [{"Time": "13:00", "Venue": "V11-G01"}]}, {"subject": "CMPG111", "number": 135, "Mo": [], "Tu": [{"Time": "14:30", "Venue": "V03-103"}, {"Time": "16:00", "Venue": "V03-103"}], "We": [], "Th": [{"Time": "09:30", "Venue": "V03-103"}], "Fr": [{"Time": "07:30", "Venue": "V03-103"}]}, {"subject": "CMPG112B", "number": 136, "Mo": [], "Tu": [{"Time": "11:00", "Venue": "V03-103"}], "We": [], "Th": [{"Time": "13:00", "Venue": "V03-103"}], "Fr": [{"Time": "14:30", "Venue": "V03-103"}, {"Time": "16:00", "Venue": "V03-103"}]}, {"subject": "CMPG112E", "number": 137, "Mo": [{"Time": "11:00", "Venue": "V03-103"}], "Tu": [], "We": [{"Time": "07:30", "Venue": "V03-103"}, {"Time": "09:30", "Venue": "V03-103"}], "Th": [], "Fr": [{"Time": "09:30", "Venue": "V03-103"}]}, {"subject": "CMPG211", "number": 138, "Mo": [{"Time": "07:30", "Venue": "V03-103"}], "Tu": [{"Time": "13:00", "Venue": "V03-103"}], "We": [], "Th": [{"Time": "14:30", "Venue": "V03-103"}, {"Time": "16:00", "Venue": "V03-103"}], "Fr": []}, {"subject": "CMPG212", "number": 139, "Mo": [{"Time": "13:00", "Venue": "V03-103"}, {"Time": "14:30", "Venue": "V03-103"}], "Tu": [{"Time": "09:30", "Venue": "V03-103"}], "We": [{"Time": "11:00", "Venue": "V03-103"}], "Th": [], "Fr": []}, {"subject": "CMPG213", "number": 140, "Mo": [], "Tu": [], "We": [], "Th": [], "Fr": [{"Time": "14:30", "Venue": "V12-G05"}, {"Time": "16:00", "Venue": "V12-G05"}]}, {"subject": "CMPG214", "number": 141, "Mo": [], "Tu": [], "We": [], "Th": [], "Fr": [{"Time": "07:30", "Venue": "V12-G02"}]}, {"subject": "CMPG215", "number": 142, "Mo": [], "Tu": [], "We": [], "Th": [{"Time": "09:30", "Venue": "V07-G04"}], "Fr": []}, {"subject": "CMPG311", "number": 143, "Mo": [], "Tu": [], "We": [{"Time": "14:30", "Venue": "V03-103"}], "Th": [], "Fr": [{"Time": "11:00", "Venue": "V03-103"}]}, {"subject": "CMPG312", "number": 144, "Mo": [{"Time": "09:30", "Venue": "V03-103"}], "Tu": [], "We": [{"Time": "16:00", "Venue": "V03-103"}], "Th": [], "Fr": []}, {"subject": "CMPG313", "number": 145, "Mo": [{"Time": "16:00", "Venue": "V03-103"}], "Tu": [], "We": [{"Time": "13:00", "Venue": "V03-103"}], "Th": [], "Fr": []}, {"subject": "CMPG315", "number": 146, "Mo": [], "Tu": [{"Time": "07:30", "Venue": "V03-103"}], "We": [], "Th": [], "Fr": [{"Time": "13:00", "Venue": "V03-103"}]}, {"subject": "COMS113", "number": 147, "Mo": [], "Tu": [], "We": [{"Time": "14:30", "Venue": "V31-G10"}], "Th": [], "Fr": [{"Time": "11:00", "Venue": "V31-G10"}]}, {"subject": "COMS114", "number": 148, "Mo": [{"Time": "07:30", "Venue": "V31-G10"}], "Tu": [], "We": [], "Th": [{"Time": "11:00", "Venue": "V31-G10"}], "Fr": []}, {"subject": "COMS212", "number": 149, "Mo": [], "Tu": [], "We": [], "Th": [{"Time": "09:30", "Venue": "V31-G02"}], "Fr": []}, {"subject": "COMS213", "number": 150, "Mo": [], "Tu": [{"Time": "16:00", "Venue": "V31-G10"}], "We": [{"Time": "16:00", "Venue": "V31-G10"}], "Th": [], "Fr": []}, {"subject": "COMS214", "number": 151, "Mo": [], "Tu": [{"Time": "07:30", "Venue": "V31-G10"}], "We": [], "Th": [{"Time": "13:00", "Venue": "V31-G10"}], "Fr": []}, {"subject": "COMS311", "number": 152, "Mo": [], "Tu": [{"Time": "14:30", "Venue": "V31-G10"}], "We": [], "Th": [], "Fr": [{"Time": "09:30", "Venue": "V31-G10"}]}, {"subject": "COMS312", "number": 153, "Mo": [], "Tu": [{"Time": "13:00", "Venue": "V31-G02"}], "We": [], "Th": [{"Time": "13:00", "Venue": "V31-G02"}], "Fr": []}, {"subject": "COMS313", "number": 154, "Mo": [], "Tu": [{"Time": "09:30", "Venue": "V31-G02"}], "We": [], "Th": [], "Fr": [{"Time": "07:30", "Venue": "V31-G02"}]}, {"subject": "CTEE212", "number": 155, "Mo": [], "Tu": [], "We": [], "Th": [{"Time": "14:30", "Venue": "V17-G15"}, {"Time": "16:00", "Venue": "V17-G15"}], "Fr": []}, {"subject": "CTEE312", "number": 156, "Mo": [{"Time": "14:30", "Venue": "V17-G15"}, {"Time": "16:00", "Venue": "V17-G15"}], "Tu": [], "We": [{"Time": "14:30", "Venue": "V17-G15"}], "Th": [], "Fr": [{"Time": "16:00", "Venue": "V17-G15"}]}, {"subject": "CTEE411", "number": 157, "Mo": [], "Tu": [], "We": [], "Th": [], "Fr": [{"Time": "14:30", "Venue": "V17-G08"}]}, {"subject": "CTEE412", "number": 158, "Mo": [], "Tu": [], "We": [], "Th": [], "Fr": [{"Time": "14:30", "Venue": "V17-G08"}]}, {"subject": "CULV211", "number": 159, "Mo": [], "Tu": [], "We": [], "Th": [{"Time": "09:30", "Venue": "V25-G03"}], "Fr": []}, {"subject": "ECOD512", "number": 160, "Mo": [], "Tu": [], "We": [], "Th": [], "Fr": [{"Time": "14:30", "Venue": "V9A-104"}]}, {"subject": "ECOE112", "number": 161, "Mo": [{"Time": "07:30", "Venue": "V9C-G01"}], "Tu": [], "We": [], "Th": [{"Time": "14:30", "Venue": "V9C-G01"}], "Fr": []}, {"subject": "ECOE212", "number": 162, "Mo": [{"Time": "07:30", "Venue": "V12-G01"}], "Tu": [], "We": [], "Th": [{"Time": "14:30", "Venue": "V12-G01"}], "Fr": []}, {"subject": "ECOE312", "number": 163, "Mo": [], "Tu": [], "We": [{"Time": "13:00", "Venue": "V12-G04"}], "Th": [], "Fr": []}, {"subject": "ECOE412", "number": 164, "Mo": [{"Time": "14:30", "Venue": "V9C-G01"}], "Tu": [], "We": [], "Th": [{"Time": "07:30", "Venue": "V9C-G01"}], "Fr": []}, {"subject": "ECON112E", "number": 165, "Mo": [], "Tu": [], "We": [], "Th": [], "Fr": [{"Time": "14:30", "Venue": "V25-G06"}]}, {"subject": "ECON112U", "number": 166, "Mo": [{"Time": "09:30", "Venue": "V12-G05"}], "Tu": [], "We": [{"Time": "16:00", "Venue": "V12-G05"}], "Th": [], "Fr": []}, {"subject": "ECON112V", "number": 167, "Mo": [{"Time": "07:30", "Venue": "V12-G06"}], "Tu": [], "We": [], "Th": [{"Time": "14:30", "Venue": "V12-G06"}], "Fr": []}, {"subject": "ECON112a", "number": 168, "Mo": [{"Time": "09:30", "Venue": "V9C-G01"}], "Tu": [], "We": [{"Time": "16:00", "Venue": "V9C-G01"}], "Th": [], "Fr": []}, {"subject": "ECON211E", "number": 169, "Mo": [], "Tu": [], "We": [{"Time": "13:00", "Venue": "V25-G01"}], "Th": [], "Fr": []}, {"subject": "ECON312", "number": 170, "Mo": [], "Tu": [], "We": [{"Time": "14:30", "Venue": "V25-G01"}], "Th": [], "Fr": [{"Time": "11:00", "Venue": "V25-G01"}]}, {"subject": "ECON313", "number": 171, "Mo": [], "Tu": [], "We": [{"Time": "07:30", "Venue": "V25-G06"}], "Th": [], "Fr": [{"Time": "09:30", "Venue": "V25-G06"}]}, {"subject": "ECON314", "number": 172, "Mo": [], "Tu": [], "We": [], "Th": [], "Fr": [{"Time": "07:30", "Venue": "V12-G06"}]}, {"subject": "EDCC114B", "number": 173, "Mo": [], "Tu": [{"Time": "07:30", "Venue": "V25-G06"}], "We": [], "Th": [], "Fr": []}, {"subject": "EDCC114E", "number": 174, "Mo": [], "Tu": [], "We": [], "Th": [{"Time": "09:30", "Venue": "V25-G08"}], "Fr": []}, {"subject": "EDCC114a", "number": 175, "Mo": [], "Tu": [{"Time": "13:00", "Venue": "V07-G04"}], "We": [], "Th": [], "Fr": []}, {"subject": "EDCC115B", "number": 176, "Mo": [], "Tu": [{"Time": "16:00", "Venue": "V25-G08"}], "We": [], "Th": [], "Fr": []}, {"subject": "EDCC115E", "number": 177, "Mo": [], "Tu": [{"Time": "13:00", "Venue": "V12-G02"}], "We": [], "Th": [], "Fr": []}, {"subject": "EDCC115a", "number": 178, "Mo": [], "Tu": [], "We": [], "Th": [], "Fr": [{"Time": "13:00", "Venue": "V06-111"}]}, {"subject": "EDCC116E", "number": 179, "Mo": [], "Tu": [], "We": [{"Time": "09:30", "Venue": "V9A-G13"}], "Th": [], "Fr": []}, {"subject": "EDCC116a", "number": 180, "Mo": [{"Time": "07:30", "Venue": "V07-K01"}], "Tu": [], "We": [], "Th": [], "Fr": []}, {"subject": "EDCC117E", "number": 181, "Mo": [{"Time": "07:30", "Venue": "V25-G03"}], "Tu": [], "We": [], "Th": [], "Fr": []}, {"subject": "EDCC117a", "number": 182, "Mo": [{"Time": "09:30", "Venue": "V12-G04"}], "Tu": [], "We": [], "Th": [], "Fr": []}, {"subject": "EDCC118E", "number": 183, "Mo": [{"Time": "13:00", "Venue": "V06-G02"}], "Tu": [], "We": [], "Th": [], "Fr": []}, {"subject": "EDCC118a", "number": 184, "Mo": [], "Tu": [{"Time": "07:30", "Venue": "V25-G09"}], "We": [], "Th": [], "Fr": []}, {"subject": "EDCC214E", "number": 185, "Mo": [], "Tu": [{"Time": "09:30", "Venue": "V25-G03"}], "We": [], "Th": [], "Fr": []}, {"subject": "EDCC214U", "number": 186, "Mo": [{"Time": "14:30", "Venue": "V25-G08"}], "Tu": [], "We": [], "Th": [], "Fr": []}, {"subject": "EDCC214a", "number": 187, "Mo": [{"Time": "14:30", "Venue": "V07-110"}], "Tu": [], "We": [], "Th": [], "Fr": []}, {"subject": "EDCC215", "number": 188, "Mo": [], "Tu": [], "We": [], "Th": [], "Fr": [{"Time": "09:30", "Venue": "V11-G02"}]}, {"subject": "EDCC215U", "number": 189, "Mo": [], "Tu": [], "We": [], "Th": [], "Fr": [{"Time": "09:30", "Venue": "V12-G02"}]}, {"subject": "EDCC215a", "number": 190, "Mo": [], "Tu": [], "We": [], "Th": [], "Fr": [{"Time": "09:30", "Venue": "V11-G02"}]}, {"subject": "EDCC216", "number": 191, "Mo": [], "Tu": [], "We": [], "Th": [], "Fr": []}, {"subject": "EDCC217", "number": 192, "Mo": [], "Tu": [], "We": [], "Th": [], "Fr": []}, {"subject": "EDCC218", "number": 193, "Mo": [], "Tu": [], "We": [], "Th": [], "Fr": []}, {"subject": "EDCC315E", "number": 194, "Mo": [], "Tu": [], "We": [], "Th": [{"Time": "13:00", "Venue": "V12-G06"}], "Fr": []}, {"subject": "EDCC315V", "number": 195, "Mo": [{"Time": "09:30", "Venue": "V12-G06"}], "Tu": [], "We": [], "Th": [], "Fr": []}, {"subject": "EDCC315a", "number": 196, "Mo": [], "Tu": [], "We": [], "Th": [], "Fr": [{"Time": "13:00", "Venue": "V12-G01"}]}, {"subject": "EDCC316", "number": 197, "Mo": [], "Tu": [], "We": [], "Th": [], "Fr": []}, {"subject": "EDCC317", "number": 198, "Mo": [], "Tu": [], "We": [], "Th": [], "Fr": []}, {"subject": "EDCC318", "number": 199, "Mo": [], "Tu": [], "We": [], "Th": [], "Fr": []}, {"subject": "EDCC411", "number": 200, "Mo": [{"Time": "09:30", "Venue": "V12-G06"}], "Tu": [], "We": [], "Th": [], "Fr": []}, {"subject": "EDCC412E", "number": 201, "Mo": [], "Tu": [], "We": [], "Th": [], "Fr": [{"Time": "11:00", "Venue": "V25-G08"}]}, {"subject": "EDCC412a", "number": 202, "Mo": [], "Tu": [], "We": [{"Time": "11:00", "Venue": "V25-G06"}], "Th": [], "Fr": []}, {"subject": "EDCC413E", "number": 203, "Mo": [], "Tu": [{"Time": "13:00", "Venue": "V12-G03"}], "We": [], "Th": [], "Fr": []}, {"subject": "EDCC414", "number": 204, "Mo": [], "Tu": [], "We": [], "Th": [{"Time": "11:00", "Venue": "V9A-G07"}], "Fr": []}, {"subject": "EDCC416", "number": 205, "Mo": [], "Tu": [], "We": [{"Time": "11:00", "Venue": "V12-G01"}], "Th": [], "Fr": []}, {"subject": "EDCC417E", "number": 206, "Mo": [], "Tu": [], "We": [{"Time": "07:30", "Venue": "V9C-G02"}], "Th": [], "Fr": []}, {"subject": "EDCC417a", "number": 207, "Mo": [], "Tu": [], "We": [], "Th": [], "Fr": [{"Time": "16:00", "Venue": "V25-G06"}]}, {"subject": "EDCC418", "number": 208, "Mo": [], "Tu": [{"Time": "11:00", "Venue": "V12-G06"}], "We": [], "Th": [], "Fr": []}, {"subject": "EDCC514", "number": 209, "Mo": [], "Tu": [], "We": [], "Th": [{"Time": "16:00", "Venue": "V12-G03"}], "Fr": []}, {"subject": "EDCC515", "number": 210, "Mo": [], "Tu": [], "We": [], "Th": [{"Time": "14:30", "Venue": "V25-G08"}], "Fr": []}, {"subject": "EDCC517", "number": 211, "Mo": [], "Tu": [{"Time": "13:00", "Venue": "V25-G06"}], "We": [], "Th": [], "Fr": []}, {"subject": "EDTC111B", "number": 212, "Mo": [], "Tu": [], "We": [], "Th": [{"Time": "13:00", "Venue": "V9A-G20"}], "Fr": []}, {"subject": "EDTC111E", "number": 213, "Mo": [], "Tu": [], "We": [], "Th": [], "Fr": [{"Time": "11:00", "Venue": "V9A-106"}]}, {"subject": "EDTC111U", "number": 214, "Mo": [], "Tu": [], "We": [{"Time": "13:00", "Venue": "V9A-106"}], "Th": [], "Fr": []}, {"subject": "EDTC111a", "number": 215, "Mo": [], "Tu": [], "We": [], "Th": [{"Time": "11:00", "Venue": "V9A-104"}], "Fr": []}, {"subject": "EDTM312B", "number": 216, "Mo": [], "Tu": [{"Time": "13:00", "Venue": "V12-G06"}], "We": [], "Th": [], "Fr": []}, {"subject": "EDTM312E", "number": 217, "Mo": [], "Tu": [], "We": [{"Time": "16:00", "Venue": "V12-G06"}], "Th": [], "Fr": []}, {"subject": "EDTM312U", "number": 218, "Mo": [], "Tu": [], "We": [], "Th": [{"Time": "11:00", "Venue": "V12-G01"}], "Fr": []}, {"subject": "EGDD411", "number": 219, "Mo": [], "Tu": [], "We": [], "Th": [{"Time": "13:00", "Venue": "V9A-G09"}], "Fr": []}, {"subject": "EGDD512", "number": 220, "Mo": [], "Tu": [], "We": [], "Th": [], "Fr": [{"Time": "09:30", "Venue": "V17-G08"}]}, {"subject": "EGDE113", "number": 221, "Mo": [{"Time": "07:30", "Venue": "V17-G08"}], "Tu": [{"Time": "11:00", "Venue": "V17-G08"}], "We": [], "Th": [], "Fr": []}, {"subject": "EGDE212", "number": 222, "Mo": [], "Tu": [{"Time": "07:30", "Venue": "V17-G08"}], "We": [], "Th": [], "Fr": [{"Time": "11:00", "Venue": "V17-G08"}]}, {"subject": "EGDE312", "number": 223, "Mo": [], "Tu": [{"Time": "09:30", "Venue": "V17-G08"}], "We": [{"Time": "11:00", "Venue": "V17-G08"}], "Th": [], "Fr": []}, {"subject": "EGDE411", "number": 224, "Mo": [], "Tu": [], "We": [{"Time": "14:30", "Venue": "V06-G10"}], "Th": [], "Fr": [{"Time": "11:00", "Venue": "V06-G10"}]}, {"subject": "EKIP212", "number": 225, "Mo": [], "Tu": [], "We": [], "Th": [], "Fr": [{"Time": "09:30", "Venue": "V25-G01"}]}, {"subject": "EKIP312", "number": 226, "Mo": [], "Tu": [], "We": [], "Th": [{"Time": "11:00", "Venue": "V25-G01"}], "Fr": []}, {"subject": "EKRP211", "number": 227, "Mo": [], "Tu": [{"Time": "13:00", "Venue": "V25-G08"}], "We": [], "Th": [{"Time": "16:00", "Venue": "V25-G08"}], "Fr": []}, {"subject": "EKRP311", "number": 228, "Mo": [{"Time": "11:00", "Venue": "V12-G01"}], "Tu": [], "We": [{"Time": "09:30", "Venue": "V12-G01"}], "Th": [], "Fr": []}, {"subject": "ENAC211B", "number": 229, "Mo": [{"Time": "16:00", "Venue": "V12-G01"}], "Tu": [], "We": [], "Th": [], "Fr": []}, {"subject": "ENAC211E", "number": 230, "Mo": [{"Time": "16:00", "Venue": "V12-G02"}], "Tu": [], "We": [], "Th": [], "Fr": []}, {"subject": "ENAF211", "number": 231, "Mo": [], "Tu": [], "We": [], "Th": [{"Time": "07:30", "Venue": "V9A-G13"}], "Fr": []}, {"subject": "ENAF311", "number": 232, "Mo": [], "Tu": [{"Time": "07:30", "Venue": "V9A-G13"}], "We": [], "Th": [], "Fr": []}, {"subject": "ENAF411", "number": 233, "Mo": [], "Tu": [], "We": [{"Time": "14:30", "Venue": "V12-G03"}], "Th": [], "Fr": []}, {"subject": "ENFF111", "number": 234, "Mo": [], "Tu": [{"Time": "11:00", "Venue": "V9A-G13"}], "We": [], "Th": [], "Fr": []}, {"subject": "ENFF211", "number": 235, "Mo": [], "Tu": [], "We": [], "Th": [{"Time": "11:00", "Venue": "V07-110"}], "Fr": []}, {"subject": "ENFF311", "number": 236, "Mo": [], "Tu": [], "We": [], "Th": [], "Fr": [{"Time": "09:30", "Venue": "V06-111"}]}, {"subject": "ENFF411", "number": 237, "Mo": [], "Tu": [{"Time": "11:00", "Venue": "V25-G07"}], "We": [], "Th": [], "Fr": []}, {"subject": "ENFI111", "number": 238, "Mo": [], "Tu": [], "We": [{"Time": "11:00", "Venue": "V06-111"}], "Th": [], "Fr": []}, {"subject": "ENFI211", "number": 239, "Mo": [], "Tu": [], "We": [], "Th": [{"Time": "13:00", "Venue": "V07-110"}], "Fr": []}, {"subject": "ENFI311", "number": 240, "Mo": [], "Tu": [], "We": [{"Time": "11:00", "Venue": "V06-G10"}], "Th": [], "Fr": []}, {"subject": "ENFI411", "number": 241, "Mo": [], "Tu": [], "We": [{"Time": "13:00", "Venue": "V07-110"}], "Th": [], "Fr": []}, {"subject": "ENGD416", "number": 242, "Mo": [], "Tu": [], "We": [], "Th": [{"Time": "09:30", "Venue": "V06-111"}], "Fr": []}, {"subject": "ENGD417", "number": 243, "Mo": [], "Tu": [], "We": [], "Th": [{"Time": "09:30", "Venue": "V06-111"}], "Fr": []}, {"subject": "ENGD512", "number": 244, "Mo": [], "Tu": [], "We": [{"Time": "07:30", "Venue": "V06-111"}], "Th": [], "Fr": []}, {"subject": "ENGV111", "number": 245, "Mo": [{"Time": "09:30", "Venue": "V25-G07"}], "Tu": [], "We": [{"Time": "16:00", "Venue": "V25-G07"}], "Th": [], "Fr": []}, {"subject": "ENGV211", "number": 246, "Mo": [], "Tu": [{"Time": "14:30", "Venue": "V25-G03"}], "We": [], "Th": [], "Fr": [{"Time": "07:30", "Venue": "V25-G03"}]}, {"subject": "ENGV311", "number": 247, "Mo": [], "Tu": [], "We": [], "Th": [{"Time": "09:30", "Venue": "V07-K01"}], "Fr": []}, {"subject": "ENGV411", "number": 248, "Mo": [], "Tu": [], "We": [{"Time": "07:30", "Venue": "V06-111"}], "Th": [], "Fr": []}, {"subject": "ENIP211", "number": 249, "Mo": [], "Tu": [{"Time": "13:00", "Venue": "V06-111"}], "We": [], "Th": [{"Time": "16:00", "Venue": "V06-111"}], "Fr": []}, {"subject": "ENIP311", "number": 250, "Mo": [{"Time": "14:30", "Venue": "V07-G04"}], "Tu": [], "We": [], "Th": [{"Time": "07:30", "Venue": "V07-G04"}], "Fr": []}, {"subject": "ENIP411", "number": 251, "Mo": [], "Tu": [], "We": [], "Th": [{"Time": "16:00", "Venue": "V06-G10"}], "Fr": []}, {"subject": "ENLL111", "number": 252, "Mo": [], "Tu": [{"Time": "07:30", "Venue": "V25-G01"}], "We": [], "Th": [], "Fr": [{"Time": "13:00", "Venue": "V25-G01"}]}, {"subject": "ENLL211", "number": 253, "Mo": [{"Time": "09:30", "Venue": "V07-206"}], "Tu": [], "We": [], "Th": [], "Fr": [{"Time": "14:30", "Venue": "V07-206"}]}, {"subject": "ENLL311", "number": 254, "Mo": [], "Tu": [{"Time": "09:30", "Venue": "V9A-G07"}], "We": [{"Time": "11:00", "Venue": "V9A-G07"}], "Th": [], "Fr": []}, {"subject": "ENLS112", "number": 255, "Mo": [], "Tu": [{"Time": "07:30", "Venue": "V25-G08"}], "We": [], "Th": [], "Fr": [{"Time": "13:00", "Venue": "V25-G08"}]}, {"subject": "ETEE213", "number": 256, "Mo": [], "Tu": [{"Time": "14:30", "Venue": "V17-G19"}], "We": [{"Time": "16:00", "Venue": "V17-G19"}], "Th": [], "Fr": [{"Time": "14:30", "Venue": "V17-G19"}, {"Time": "16:00", "Venue": "V17-G19"}]}, {"subject": "ETEE312", "number": 257, "Mo": [{"Time": "14:30", "Venue": "V17-G19"}, {"Time": "16:00", "Venue": "V17-G19"}], "Tu": [{"Time": "16:00", "Venue": "V17-G19"}], "We": [{"Time": "14:30", "Venue": "V17-G19"}], "Th": [], "Fr": []}, {"subject": "ETEE411", "number": 258, "Mo": [], "Tu": [], "We": [], "Th": [{"Time": "14:30", "Venue": "V17-G19"}, {"Time": "16:00", "Venue": "V17-G19"}], "Fr": []}, {"subject": "ETIE212", "number": 259, "Mo": [], "Tu": [], "We": [{"Time": "11:00", "Venue": "Dept-6"}], "Th": [], "Fr": []}, {"subject": "FETC111", "number": 260, "Mo": [], "Tu": [], "We": [{"Time": "16:00", "Venue": "V17-G08"}], "Th": [{"Time": "14:30", "Venue": "V17-G08"}], "Fr": []}, {"subject": "FETM111", "number": 261, "Mo": [], "Tu": [], "We": [], "Th": [{"Time": "07:30", "Venue": "V17-G08"}], "Fr": []}, {"subject": "FETP111", "number": 262, "Mo": [], "Tu": [], "We": [{"Time": "13:00", "Venue": "V17-G08"}], "Th": [], "Fr": []}, {"subject": "FETW211", "number": 263, "Mo": [], "Tu": [{"Time": "07:30", "Venue": "V17-G17"}, {"Time": "09:30", "Venue": "V17-G17"}], "We": [{"Time": "11:00", "Venue": "V17-G17"}], "Th": [], "Fr": [{"Time": "13:00", "Venue": "V17-G17"}]}, {"subject": "FINM271", "number": 264, "Mo": [], "Tu": [], "We": [{"Time": "07:30", "Venue": "V12-G05"}], "Th": [], "Fr": [{"Time": "09:30", "Venue": "V12-G05"}]}, {"subject": "FINM371", "number": 265, "Mo": [], "Tu": [], "We": [], "Th": [], "Fr": [{"Time": "13:00", "Venue": "V12-G04"}]}, {"subject": "FMAN271", "number": 266, "Mo": [], "Tu": [{"Time": "11:00", "Venue": "V9C-G02"}], "We": [], "Th": [], "Fr": [{"Time": "09:30", "Venue": "V9C-G02"}]}, {"subject": "FMAN371", "number": 267, "Mo": [{"Time": "13:00", "Venue": "V04-K03"}], "Tu": [], "We": [{"Time": "07:30", "Venue": "V04-K03"}], "Th": [], "Fr": []}, {"subject": "FREB111", "number": 268, "Mo": [], "Tu": [], "We": [], "Th": [{"Time": "14:30", "Venue": "V12-G04"}], "Fr": []}, {"subject": "FREN111", "number": 269, "Mo": [{"Time": "14:30", "Venue": "V31-G02"}], "Tu": [], "We": [], "Th": [], "Fr": []}, {"subject": "FREN211", "number": 270, "Mo": [], "Tu": [], "We": [], "Th": [{"Time": "16:00", "Venue": "V9C-G01"}], "Fr": []}, {"subject": "FREN311", "number": 271, "Mo": [], "Tu": [], "We": [], "Th": [], "Fr": [{"Time": "11:00", "Venue": "Dept-2"}]}, {"subject": "GEOD411", "number": 272, "Mo": [], "Tu": [], "We": [], "Th": [], "Fr": [{"Time": "07:30", "Venue": "V07-206"}]}, {"subject": "GEOD512", "number": 273, "Mo": [], "Tu": [{"Time": "14:30", "Venue": "V9C-G01"}, {"Time": "16:00", "Venue": "V9C-G01"}], "We": [], "Th": [], "Fr": []}, {"subject": "GEOE112", "number": 274, "Mo": [], "Tu": [], "We": [], "Th": [{"Time": "07:30", "Venue": "V25-G06"}], "Fr": []}, {"subject": "GEOE212", "number": 275, "Mo": [{"Time": "11:00", "Venue": "V9C-G01"}], "Tu": [], "We": [{"Time": "07:30", "Venue": "V9C-G01"}, {"Time": "09:30", "Venue": "V9C-G01"}], "Th": [], "Fr": []}, {"subject": "GEOE312", "number": 276, "Mo": [{"Time": "07:30", "Venue": "V07-110"}], "Tu": [], "We": [], "Th": [{"Time": "14:30", "Venue": "V07-110"}, {"Time": "16:00", "Venue": "V07-110"}], "Fr": []}, {"subject": "GEOE411", "number": 277, "Mo": [], "Tu": [], "We": [], "Th": [], "Fr": [{"Time": "09:30", "Venue": "V07-110"}]}, {"subject": "GEOG111", "number": 278, "Mo": [], "Tu": [{"Time": "13:00", "Venue": "V9C-G01"}], "We": [], "Th": [], "Fr": []}, {"subject": "GEOG211", "number": 279, "Mo": [], "Tu": [], "We": [], "Th": [{"Time": "07:30", "Venue": "V25-G01"}], "Fr": []}, {"subject": "GEOG311", "number": 280, "Mo": [{"Time": "11:00", "Venue": "V9A-104"}], "Tu": [], "We": [{"Time": "07:30", "Venue": "V9A-104"}, {"Time": "09:30", "Venue": "V9A-104"}], "Th": [], "Fr": [{"Time": "09:30", "Venue": "V9A-104"}]}, {"subject": "GEOS211", "number": 281, "Mo": [{"Time": "13:00", "Venue": "V07-206"}], "Tu": [], "We": [], "Th": [], "Fr": []}, {"subject": "GERB111", "number": 282, "Mo": [], "Tu": [], "We": [], "Th": [{"Time": "14:30", "Venue": "V9B-G02"}], "Fr": []}, {"subject": "GERM111", "number": 283, "Mo": [], "Tu": [{"Time": "07:30", "Venue": "V31-G02"}], "We": [], "Th": [{"Time": "07:30", "Venue": "V31-G02"}], "Fr": []}, {"subject": "GERM211", "number": 284, "Mo": [], "Tu": [], "We": [], "Th": [], "Fr": [{"Time": "09:30", "Venue": "V07-G04"}]}, {"subject": "HISD411", "number": 285, "Mo": [{"Time": "11:00", "Venue": "V9B-G02"}], "Tu": [], "We": [{"Time": "09:30", "Venue": "V9B-G02"}], "Th": [], "Fr": []}, {"subject": "HISD512", "number": 286, "Mo": [], "Tu": [{"Time": "09:30", "Venue": "V07-110"}], "We": [], "Th": [], "Fr": []}, {"subject": "HISE112", "number": 287, "Mo": [], "Tu": [{"Time": "14:30", "Venue": "V07-G04"}], "We": [], "Th": [], "Fr": [{"Time": "07:30", "Venue": "V07-G04"}]}, {"subject": "HISE212", "number": 288, "Mo": [], "Tu": [{"Time": "09:30", "Venue": "V9A-G09"}], "We": [{"Time": "11:00", "Venue": "V9A-G09"}], "Th": [], "Fr": []}, {"subject": "HISE312", "number": 289, "Mo": [], "Tu": [], "We": [{"Time": "07:30", "Venue": "V06-G08"}], "Th": [], "Fr": [{"Time": "09:30", "Venue": "V06-G08"}]}, {"subject": "HISE411", "number": 290, "Mo": [], "Tu": [], "We": [], "Th": [], "Fr": [{"Time": "11:00", "Venue": "V9A-G13"}]}, {"subject": "HIST112", "number": 291, "Mo": [], "Tu": [{"Time": "16:00", "Venue": "V12-G03"}], "We": [], "Th": [{"Time": "09:30", "Venue": "V12-G03"}], "Fr": []}, {"subject": "HIST212", "number": 292, "Mo": [], "Tu": [{"Time": "09:30", "Venue": "V9B-G01"}], "We": [{"Time": "11:00", "Venue": "V9B-G01"}], "Th": [], "Fr": []}, {"subject": "HIST213", "number": 293, "Mo": [{"Time": "11:00", "Venue": "V9B-G01"}], "Tu": [], "We": [{"Time": "09:30", "Venue": "V9B-G01"}], "Th": [], "Fr": []}, {"subject": "HIST312", "number": 294, "Mo": [], "Tu": [], "We": [], "Th": [{"Time": "14:30", "Venue": "V12-G03"}], "Fr": []}, {"subject": "HISV211", "number": 295, "Mo": [], "Tu": [], "We": [{"Time": "13:00", "Venue": "V06-G07"}], "Th": [], "Fr": []}, {"subject": "HRMA211", "number": 296, "Mo": [], "Tu": [], "We": [], "Th": [], "Fr": [{"Time": "13:00", "Venue": "V25-G09"}]}, {"subject": "ICAT111B", "number": 297, "Mo": [], "Tu": [], "We": [], "Th": [], "Fr": [{"Time": "07:30", "Venue": "V06-G02"}]}, {"subject": "ICAT111C", "number": 298, "Mo": [], "Tu": [], "We": [], "Th": [{"Time": "07:30", "Venue": "V25-G07"}], "Fr": []}, {"subject": "ICAT111D", "number": 299, "Mo": [], "Tu": [], "We": [{"Time": "11:00", "Venue": "V12-G04"}], "Th": [], "Fr": []}, {"subject": "ICAT111E", "number": 300, "Mo": [{"Time": "07:30", "Venue": "V9B-G02"}], "Tu": [], "We": [], "Th": [], "Fr": []}, {"subject": "ICOM111", "number": 301, "Mo": [], "Tu": [], "We": [], "Th": [], "Fr": [{"Time": "16:00", "Venue": "V11-G02"}]}, {"subject": "INTD411", "number": 302, "Mo": [], "Tu": [], "We": [], "Th": [], "Fr": [{"Time": "07:30", "Venue": "V06-G08"}]}, {"subject": "IOPS111", "number": 303, "Mo": [{"Time": "16:00", "Venue": "V12-G06"}], "Tu": [], "We": [{"Time": "13:00", "Venue": "V12-G06"}], "Th": [], "Fr": []}, {"subject": "IOPS211", "number": 304, "Mo": [], "Tu": [], "We": [], "Th": [{"Time": "11:00", "Venue": "V12-G05"}], "Fr": []}, {"subject": "IOPS311", "number": 305, "Mo": [{"Time": "07:30", "Venue": "V12-G04"}], "Tu": [], "We": [], "Th": [], "Fr": [{"Time": "14:30", "Venue": "V12-G04"}]}, {"subject": "ITEE312", "number": 306, "Mo": [{"Time": "11:00", "Venue": "V17-G13"}], "Tu": [], "We": [{"Time": "07:30", "Venue": "V17-G13"}, {"Time": "09:30", "Venue": "V17-G13"}], "Th": [], "Fr": [{"Time": "09:30", "Venue": "V17-G13"}]}, {"subject": "ITEE412", "number": 307, "Mo": [], "Tu": [{"Time": "14:30", "Venue": "V17-G13"}, {"Time": "16:00", "Venue": "V17-G13"}], "We": [], "Th": [{"Time": "09:30", "Venue": "V17-G13"}], "Fr": [{"Time": "07:30", "Venue": "V17-G13"}]}, {"subject": "ITEE413", "number": 308, "Mo": [], "Tu": [{"Time": "14:30", "Venue": "V17-G13"}, {"Time": "16:00", "Venue": "V17-G13"}], "We": [], "Th": [{"Time": "09:30", "Venue": "V17-G13"}], "Fr": [{"Time": "07:30", "Venue": "V17-G13"}]}, {"subject": "ITSP111", "number": 309, "Mo": [], "Tu": [{"Time": "14:30", "Venue": "V9A-102"}], "We": [], "Th": [{"Time": "09:30", "Venue": "V9A-102"}], "Fr": []}, {"subject": "ITSP113", "number": 310, "Mo": [{"Time": "13:00", "Venue": "V9A-102"}], "Tu": [], "We": [], "Th": [], "Fr": [{"Time": "07:30", "Venue": "V9A-102"}]}, {"subject": "ITSP114", "number": 311, "Mo": [], "Tu": [{"Time": "07:30", "Venue": "V9A-102"}], "We": [], "Th": [{"Time": "07:30", "Venue": "V9A-102"}], "Fr": []}, {"subject": "IURI111", "number": 312, "Mo": [], "Tu": [{"Time": "14:30", "Venue": "V25-G01"}], "We": [], "Th": [], "Fr": [{"Time": "07:30", "Venue": "V25-G01"}]}, {"subject": "IURI171", "number": 313, "Mo": [], "Tu": [{"Time": "16:00", "Venue": "V06-G02"}], "We": [], "Th": [{"Time": "09:30", "Venue": "V06-G02"}], "Fr": []}, {"subject": "IURI173", "number": 314, "Mo": [], "Tu": [{"Time": "13:00", "Venue": "V11-G02"}], "We": [], "Th": [{"Time": "16:00", "Venue": "V11-G02"}], "Fr": []}, {"subject": "IURI174", "number": 315, "Mo": [], "Tu": [{"Time": "11:00", "Venue": "V12-G01"}], "We": [], "Th": [], "Fr": [{"Time": "14:30", "Venue": "V12-G01"}]}, {"subject": "IURI212", "number": 316, "Mo": [], "Tu": [{"Time": "13:00", "Venue": "V25-G01"}], "We": [], "Th": [{"Time": "16:00", "Venue": "V25-G01"}], "Fr": []}, {"subject": "IURI213", "number": 317, "Mo": [], "Tu": [{"Time": "09:30", "Venue": "V9C-G01"}], "We": [{"Time": "11:00", "Venue": "V9C-G01"}], "Th": [], "Fr": []}, {"subject": "IURI272", "number": 318, "Mo": [{"Time": "11:00", "Venue": "V25-G03"}], "Tu": [], "We": [{"Time": "09:30", "Venue": "V25-G03"}], "Th": [], "Fr": []}, {"subject": "IURI273", "number": 319, "Mo": [{"Time": "09:30", "Venue": "V25-G03"}], "Tu": [], "We": [{"Time": "16:00", "Venue": "V25-G03"}], "Th": [], "Fr": []}, {"subject": "IURI274", "number": 320, "Mo": [], "Tu": [], "We": [{"Time": "14:30", "Venue": "V12-G01"}], "Th": [], "Fr": [{"Time": "11:00", "Venue": "V12-G01"}]}, {"subject": "IURI275", "number": 321, "Mo": [], "Tu": [{"Time": "13:00", "Venue": "V25-G01"}], "We": [], "Th": [{"Time": "16:00", "Venue": "V25-G01"}], "Fr": []}, {"subject": "IURI311", "number": 322, "Mo": [], "Tu": [{"Time": "14:30", "Venue": "V06-G07"}], "We": [], "Th": [], "Fr": [{"Time": "07:30", "Venue": "V06-G07"}]}, {"subject": "IURI312", "number": 323, "Mo": [{"Time": "14:30", "Venue": "V9B-G02"}], "Tu": [], "We": [], "Th": [{"Time": "07:30", "Venue": "V9B-G02"}], "Fr": []}, {"subject": "IURI313", "number": 324, "Mo": [], "Tu": [{"Time": "07:30", "Venue": "V12-G06"}], "We": [], "Th": [], "Fr": [{"Time": "13:00", "Venue": "V12-G06"}]}, {"subject": "IURI373", "number": 325, "Mo": [], "Tu": [], "We": [], "Th": [{"Time": "16:00", "Venue": "V12-G02"}], "Fr": []}, {"subject": "IURI377", "number": 326, "Mo": [], "Tu": [], "We": [{"Time": "07:30", "Venue": "V12-G01"}], "Th": [], "Fr": [{"Time": "09:30", "Venue": "V12-G01"}]}, {"subject": "IURI412", "number": 327, "Mo": [], "Tu": [{"Time": "16:00", "Venue": "V12-G01"}], "We": [], "Th": [{"Time": "09:30", "Venue": "V12-G01"}], "Fr": []}, {"subject": "KCOM111", "number": 328, "Mo": [], "Tu": [], "We": [{"Time": "13:00", "Venue": "V25-G08"}], "Th": [], "Fr": []}, {"subject": "KCOM112", "number": 329, "Mo": [], "Tu": [{"Time": "14:30", "Venue": "V12-G05"}], "We": [], "Th": [], "Fr": [{"Time": "07:30", "Venue": "V12-G05"}]}, {"subject": "KCOM211", "number": 330, "Mo": [], "Tu": [{"Time": "11:00", "Venue": "V31-G02"}], "We": [{"Time": "13:00", "Venue": "V31-G02"}], "Th": [], "Fr": []}, {"subject": "LAAD411", "number": 331, "Mo": [], "Tu": [], "We": [], "Th": [], "Fr": [{"Time": "07:30", "Venue": "V9A-G13"}]}, {"subject": "LABD411", "number": 332, "Mo": [], "Tu": [{"Time": "14:30", "Venue": "V25-G07"}], "We": [], "Th": [], "Fr": [{"Time": "07:30", "Venue": "V25-G07"}]}, {"subject": "LAND411", "number": 333, "Mo": [], "Tu": [{"Time": "07:30", "Venue": "V11-G07"}], "We": [], "Th": [], "Fr": [{"Time": "13:00", "Venue": "V11-G07"}]}, {"subject": "LARM111E", "number": 334, "Mo": [], "Tu": [], "We": [{"Time": "11:00", "Venue": "V12-G05"}], "Th": [], "Fr": []}, {"subject": "LARM111a", "number": 335, "Mo": [], "Tu": [], "We": [{"Time": "07:30", "Venue": "V06-G07"}], "Th": [], "Fr": [{"Time": "09:30", "Venue": "V06-G07"}]}, {"subject": "LARM112", "number": 336, "Mo": [{"Time": "14:30", "Venue": "V12-G03"}], "Tu": [], "We": [], "Th": [{"Time": "07:30", "Venue": "V12-G03"}], "Fr": []}, {"subject": "LARM212", "number": 337, "Mo": [], "Tu": [{"Time": "16:00", "Venue": "V25-G01"}], "We": [], "Th": [{"Time": "09:30", "Venue": "V25-G01"}], "Fr": []}, {"subject": "LARM311", "number": 338, "Mo": [], "Tu": [], "We": [], "Th": [{"Time": "07:30", "Venue": "V12-G04"}], "Fr": []}, {"subject": "LIFD411", "number": 339, "Mo": [{"Time": "14:30", "Venue": "V9A-G03"}], "Tu": [], "We": [], "Th": [{"Time": "07:30", "Venue": "V9A-G03"}], "Fr": []}, {"subject": "LIFD512", "number": 340, "Mo": [], "Tu": [], "We": [{"Time": "13:00", "Venue": "V9A-G09"}], "Th": [], "Fr": []}, {"subject": "LIFE112E", "number": 341, "Mo": [], "Tu": [{"Time": "11:00", "Venue": "V9A-G03"}], "We": [], "Th": [{"Time": "13:00", "Venue": "V9A-G03"}], "Fr": [{"Time": "14:30", "Venue": "V9A-G03"}, {"Time": "16:00", "Venue": "V9A-G03"}]}, {"subject": "LIFE212", "number": 342, "Mo": [{"Time": "13:00", "Venue": "V9A-G03"}], "Tu": [], "We": [{"Time": "14:30", "Venue": "V9A-G03"}, {"Time": "16:00", "Venue": "V9A-G03"}], "Th": [], "Fr": [{"Time": "11:00", "Venue": "V9A-G03"}]}, {"subject": "LIFE312", "number": 343, "Mo": [{"Time": "09:30", "Venue": "V9A-G03"}], "Tu": [{"Time": "14:30", "Venue": "V9A-G03"}, {"Time": "16:00", "Venue": "V9A-G03"}], "We": [], "Th": [], "Fr": [{"Time": "07:30", "Venue": "V9A-G03"}]}, {"subject": "LIFE411", "number": 344, "Mo": [{"Time": "07:30", "Venue": "V9A-G03"}], "Tu": [{"Time": "07:30", "Venue": "V9A-G03"}, {"Time": "09:30", "Venue": "V9A-G03"}], "We": [{"Time": "13:00", "Venue": "V9A-G03"}], "Th": [], "Fr": []}, {"subject": "LLOD512", "number": 345, "Mo": [{"Time": "11:00", "Venue": "V12-G03"}], "Tu": [], "We": [{"Time": "09:30", "Venue": "V12-G03"}], "Th": [], "Fr": []}, {"subject": "LOCE411", "number": 346, "Mo": [], "Tu": [], "We": [], "Th": [], "Fr": [{"Time": "13:00", "Venue": "V07-110"}]}, {"subject": "LOPE311", "number": 347, "Mo": [], "Tu": [{"Time": "11:00", "Venue": "V06-111"}], "We": [], "Th": [], "Fr": [{"Time": "14:30", "Venue": "V06-111"}]}, {"subject": "LOPV111", "number": 348, "Mo": [], "Tu": [], "We": [], "Th": [{"Time": "16:00", "Venue": "V07-G04"}], "Fr": []}, {"subject": "LOSE211", "number": 349, "Mo": [{"Time": "09:30", "Venue": "V07-110"}], "Tu": [], "We": [{"Time": "16:00", "Venue": "V07-110"}], "Th": [], "Fr": []}, {"subject": "LPRA111", "number": 350, "Mo": [{"Time": "16:00", "Venue": "V31-G02"}], "Tu": [], "We": [], "Th": [], "Fr": [{"Time": "14:30", "Venue": "V31-G02"}]}, {"subject": "LPRA211", "number": 351, "Mo": [{"Time": "07:30", "Venue": "V31-G01"}], "Tu": [], "We": [], "Th": [{"Time": "14:30", "Venue": "V31-G01"}], "Fr": []}, {"subject": "LPRA311", "number": 352, "Mo": [{"Time": "14:30", "Venue": "V31-G01"}], "Tu": [], "We": [], "Th": [{"Time": "07:30", "Venue": "V31-G01"}], "Fr": []}, {"subject": "LPRA312", "number": 353, "Mo": [], "Tu": [{"Time": "07:30", "Venue": "V31-G01"}], "We": [], "Th": [], "Fr": [{"Time": "13:00", "Venue": "V31-G01"}]}, {"subject": "LSIP111", "number": 354, "Mo": [], "Tu": [], "We": [{"Time": "13:00", "Venue": "V9B-G02"}], "Th": [], "Fr": []}, {"subject": "LSIP211", "number": 355, "Mo": [], "Tu": [], "We": [], "Th": [], "Fr": [{"Time": "11:00", "Venue": "V07-K01"}]}, {"subject": "LSIP311", "number": 356, "Mo": [{"Time": "13:00", "Venue": "V25-G07"}], "Tu": [], "We": [], "Th": [], "Fr": []}, {"subject": "LSIP411", "number": 357, "Mo": [], "Tu": [], "We": [{"Time": "11:00", "Venue": "V12-G06"}], "Th": [], "Fr": []}, {"subject": "LSKA211", "number": 358, "Mo": [], "Tu": [], "We": [{"Time": "07:30", "Venue": "V9A-G07"}], "Th": [], "Fr": []}, {"subject": "LSKS111E", "number": 359, "Mo": [], "Tu": [], "We": [{"Time": "16:00", "Venue": "V07-206"}], "Th": [], "Fr": []}, {"subject": "LSKS111a", "number": 360, "Mo": [], "Tu": [], "We": [{"Time": "16:00", "Venue": "V07-206"}], "Th": [], "Fr": []}, {"subject": "LSPP411", "number": 361, "Mo": [], "Tu": [], "We": [], "Th": [{"Time": "07:30", "Venue": "V25-G03"}], "Fr": []}, {"subject": "MACC271B", "number": 362, "Mo": [], "Tu": [], "We": [], "Th": [{"Time": "14:30", "Venue": "V06-G02"}], "Fr": []}, {"subject": "MACC271E", "number": 363, "Mo": [], "Tu": [{"Time": "11:00", "Venue": "V06-G02"}], "We": [], "Th": [{"Time": "13:00", "Venue": "V06-G02"}], "Fr": []}, {"subject": "MACC371", "number": 364, "Mo": [{"Time": "09:30", "Venue": "V12-G03"}], "Tu": [], "We": [], "Th": [], "Fr": [{"Time": "11:00", "Venue": "V12-G03"}]}, {"subject": "MAIP211", "number": 365, "Mo": [{"Time": "11:00", "Venue": "V25-G07"}], "Tu": [], "We": [{"Time": "09:30", "Venue": "V25-G07"}], "Th": [], "Fr": []}, {"subject": "MAIP311", "number": 366, "Mo": [], "Tu": [], "We": [], "Th": [], "Fr": [{"Time": "11:00", "Venue": "V9A-G07"}]}, {"subject": "MAIP411", "number": 367, "Mo": [], "Tu": [], "We": [], "Th": [{"Time": "14:30", "Venue": "V07-206"}], "Fr": []}, {"subject": "MATD411", "number": 368, "Mo": [], "Tu": [], "We": [], "Th": [{"Time": "09:30", "Venue": "V25-G09"}], "Fr": []}, {"subject": "MATD413", "number": 369, "Mo": [], "Tu": [{"Time": "14:30", "Venue": "V06-G10"}], "We": [], "Th": [], "Fr": [{"Time": "07:30", "Venue": "V06-G10"}]}, {"subject": "MATD512", "number": 370, "Mo": [], "Tu": [], "We": [{"Time": "07:30", "Venue": "V9A-G20"}], "Th": [], "Fr": [{"Time": "09:30", "Venue": "V9A-G20"}]}, {"subject": "MATF111", "number": 371, "Mo": [], "Tu": [], "We": [], "Th": [{"Time": "16:00", "Venue": "V12-G06"}], "Fr": []}, {"subject": "MATF111", "number": 372, "Mo": [], "Tu": [], "We": [{"Time": "07:30", "Venue": "V07-K01"}], "Th": [], "Fr": []}, {"subject": "MATH111", "number": 373, "Mo": [], "Tu": [{"Time": "14:30", "Venue": "V9B-G02"}, {"Time": "16:00", "Venue": "V9B-G02"}], "We": [], "Th": [{"Time": "09:30", "Venue": "V9B-G02"}], "Fr": [{"Time": "07:30", "Venue": "V9B-G02"}]}, {"subject": "MATH211", "number": 374, "Mo": [], "Tu": [{"Time": "11:00", "Venue": "V25-G09"}], "We": [], "Th": [{"Time": "13:00", "Venue": "V25-G09"}], "Fr": [{"Time": "14:30", "Venue": "V25-G09"}, {"Time": "16:00", "Venue": "V25-G09"}]}, {"subject": "MATH311", "number": 375, "Mo": [{"Time": "11:00", "Venue": "V07-206"}], "Tu": [], "We": [{"Time": "07:30", "Venue": "V07-206"}, {"Time": "09:30", "Venue": "V07-206"}], "Th": [], "Fr": [{"Time": "09:30", "Venue": "V07-206"}]}, {"subject": "MATH411", "number": 376, "Mo": [], "Tu": [], "We": [], "Th": [], "Fr": [{"Time": "07:30", "Venue": "Dept-5"}]}, {"subject": "MATV111", "number": 377, "Mo": [{"Time": "11:00", "Venue": "V9A-G07"}], "Tu": [], "We": [], "Th": [], "Fr": []}, {"subject": "MDAC271", "number": 378, "Mo": [], "Tu": [], "We": [], "Th": [{"Time": "13:00", "Venue": "V9C-G02"}], "Fr": [{"Time": "07:30", "Venue": "V9C-G02"}]}, {"subject": "MDAC371", "number": 379, "Mo": [], "Tu": [{"Time": "13:00", "Venue": "V04-K03"}], "We": [], "Th": [], "Fr": [{"Time": "11:00", "Venue": "V04-K03"}]}, {"subject": "MFPC111E", "number": 380, "Mo": [], "Tu": [], "We": [], "Th": [], "Fr": [{"Time": "09:30", "Venue": "V25-G09"}]}, {"subject": "MFPC111a", "number": 381, "Mo": [], "Tu": [], "We": [], "Th": [{"Time": "13:00", "Venue": "V11-G02"}], "Fr": []}, {"subject": "MFPC311", "number": 382, "Mo": [], "Tu": [], "We": [], "Th": [{"Time": "07:30", "Venue": "V11-G02"}], "Fr": []}, {"subject": "MFPC411", "number": 383, "Mo": [], "Tu": [], "We": [{"Time": "13:00", "Venue": "V12-G01"}], "Th": [], "Fr": []}, {"subject": "MLAW111E", "number": 384, "Mo": [], "Tu": [], "We": [{"Time": "07:30", "Venue": "V06-G02"}], "Th": [], "Fr": [{"Time": "09:30", "Venue": "V06-G02"}]}, {"subject": "MLAW111a", "number": 385, "Mo": [], "Tu": [{"Time": "14:30", "Venue": "V04-G03"}], "We": [], "Th": [], "Fr": [{"Time": "14:30", "Venue": "V04-G03"}]}, {"subject": "MLAW211", "number": 386, "Mo": [], "Tu": [{"Time": "09:30", "Venue": "V06-G02"}], "We": [], "Th": [{"Time": "11:00", "Venue": "V06-G02"}], "Fr": []}, {"subject": "MLIT111", "number": 387, "Mo": [], "Tu": [{"Time": "09:30", "Venue": "V07-206"}], "We": [{"Time": "11:00", "Venue": "V07-206"}], "Th": [], "Fr": []}, {"subject": "MLIT211", "number": 388, "Mo": [], "Tu": [{"Time": "11:00", "Venue": "V9A-G09"}], "We": [], "Th": [], "Fr": [{"Time": "14:30", "Venue": "V9A-G09"}]}, {"subject": "MLIT311", "number": 389, "Mo": [{"Time": "11:00", "Venue": "V07-G04"}], "Tu": [], "We": [{"Time": "09:30", "Venue": "V07-G04"}], "Th": [], "Fr": []}, {"subject": "MLIT411", "number": 390, "Mo": [], "Tu": [], "We": [], "Th": [], "Fr": [{"Time": "13:00", "Venue": "V9B-G02"}]}, {"subject": "MTEC111", "number": 391, "Mo": [], "Tu": [], "We": [{"Time": "11:00", "Venue": "V07-G04"}], "Th": [], "Fr": []}, {"subject": "MTHS111", "number": 392, "Mo": [], "Tu": [], "We": [], "Th": [{"Time": "13:00", "Venue": "V25-G06"}], "Fr": []}, {"subject": "MTHS112E", "number": 393, "Mo": [], "Tu": [], "We": [], "Th": [{"Time": "16:00", "Venue": "V06-G02"}], "Fr": []}, {"subject": "MTHS112U", "number": 394, "Mo": [], "Tu": [], "We": [{"Time": "16:00", "Venue": "V12-G01"}], "Th": [], "Fr": []}, {"subject": "MTHS112a", "number": 395, "Mo": [], "Tu": [], "We": [{"Time": "14:30", "Venue": "V25-G06"}], "Th": [], "Fr": [{"Time": "11:00", "Venue": "V25-G06"}]}, {"subject": "MTHS113", "number": 396, "Mo": [{"Time": "09:30", "Venue": "V25-G06"}], "Tu": [], "We": [{"Time": "16:00", "Venue": "V25-G06"}], "Th": [], "Fr": []}, {"subject": "MTHS119E", "number": 397, "Mo": [], "Tu": [{"Time": "16:00", "Venue": "V12-G06"}], "We": [], "Th": [{"Time": "09:30", "Venue": "V12-G06"}], "Fr": []}, {"subject": "MTHS119L", "number": 398, "Mo": [], "Tu": [], "We": [], "Th": [{"Time": "11:00", "Venue": "V11-G02"}], "Fr": [{"Time": "14:30", "Venue": "V11-G02"}]}, {"subject": "MTHS119a", "number": 399, "Mo": [], "Tu": [{"Time": "14:30", "Venue": "V9B-G01"}], "We": [], "Th": [], "Fr": [{"Time": "07:30", "Venue": "V9B-G01"}]}, {"subject": "MTHS211E", "number": 400, "Mo": [{"Time": "11:00", "Venue": "V25-G06"}], "Tu": [], "We": [{"Time": "09:30", "Venue": "V25-G06"}], "Th": [], "Fr": []}, {"subject": "MTHS212", "number": 401, "Mo": [], "Tu": [], "We": [], "Th": [], "Fr": [{"Time": "13:00", "Venue": "V9C-G02"}]}, {"subject": "MTHS311", "number": 402, "Mo": [], "Tu": [], "We": [], "Th": [], "Fr": [{"Time": "07:30", "Venue": "V07-110"}]}, {"subject": "MTLS211", "number": 403, "Mo": [], "Tu": [], "We": [], "Th": [{"Time": "09:30", "Venue": "V25-G06"}], "Fr": []}, {"subject": "NSCH111", "number": 404, "Mo": [], "Tu": [{"Time": "07:30", "Venue": "Dept-4"}], "We": [], "Th": [], "Fr": [{"Time": "13:00", "Venue": "Dept-4"}]}, {"subject": "NSFN111", "number": 405, "Mo": [], "Tu": [], "We": [], "Th": [{"Time": "14:30", "Venue": "Dept-2"}], "Fr": []}, {"subject": "NSFP111", "number": 406, "Mo": [{"Time": "14:30", "Venue": "Dept-6"}], "Tu": [], "We": [], "Th": [{"Time": "07:30", "Venue": "Dept-6"}], "Fr": []}, {"subject": "NSSP111E", "number": 407, "Mo": [], "Tu": [], "We": [], "Th": [], "Fr": [{"Time": "09:30", "Venue": "V9A-G07"}]}, {"subject": "NSSP112E", "number": 408, "Mo": [{"Time": "07:30", "Venue": "V11-G07"}], "Tu": [], "We": [], "Th": [], "Fr": []}, {"subject": "NSSP211", "number": 409, "Mo": [], "Tu": [{"Time": "16:00", "Venue": "V11-G07"}], "We": [], "Th": [{"Time": "09:30", "Venue": "V11-G07"}], "Fr": []}, {"subject": "NSTL111", "number": 410, "Mo": [], "Tu": [{"Time": "14:30", "Venue": "V11-G07"}], "We": [], "Th": [], "Fr": [{"Time": "07:30", "Venue": "V11-G07"}]}, {"subject": "NSTL211", "number": 411, "Mo": [], "Tu": [], "We": [{"Time": "07:30", "Venue": "V11-G06"}], "Th": [], "Fr": [{"Time": "11:00", "Venue": "V11-G06"}]}, {"subject": "NSTL311", "number": 412, "Mo": [{"Time": "11:00", "Venue": "V11-G06"}], "Tu": [], "We": [{"Time": "09:30", "Venue": "V11-G06"}], "Th": [], "Fr": []}, {"subject": "NSTL411", "number": 413, "Mo": [], "Tu": [{"Time": "07:30", "Venue": "V11-G06"}], "We": [], "Th": [], "Fr": [{"Time": "13:00", "Venue": "V11-G06"}]}, {"subject": "PACO411", "number": 414, "Mo": [], "Tu": [], "We": [], "Th": [{"Time": "11:00", "Venue": "V07-206"}], "Fr": []}, {"subject": "PADM111E", "number": 415, "Mo": [{"Time": "09:30", "Venue": "V25-G01"}], "Tu": [], "We": [{"Time": "16:00", "Venue": "V25-G01"}], "Th": [], "Fr": []}, {"subject": "PADM111a", "number": 416, "Mo": [], "Tu": [], "We": [{"Time": "14:30", "Venue": "Dept-7"}], "Th": [], "Fr": [{"Time": "11:00", "Venue": "Dept-7"}]}, {"subject": "PADM211", "number": 417, "Mo": [], "Tu": [], "We": [{"Time": "14:30", "Venue": "V25-G03"}], "Th": [], "Fr": [{"Time": "11:00", "Venue": "V25-G03"}]}, {"subject": "PADM311", "number": 418, "Mo": [], "Tu": [{"Time": "16:00", "Venue": "V12-G04"}], "We": [], "Th": [], "Fr": []}, {"subject": "PADM312", "number": 419, "Mo": [], "Tu": [{"Time": "07:30", "Venue": "V11-G02"}], "We": [], "Th": [], "Fr": [{"Time": "13:00", "Venue": "V11-G02"}]}, {"subject": "PEFI211", "number": 420, "Mo": [{"Time": "07:30", "Venue": "V06-G10"}], "Tu": [], "We": [], "Th": [{"Time": "14:30", "Venue": "V06-G10"}], "Fr": []}, {"subject": "PEFI311", "number": 421, "Mo": [], "Tu": [], "We": [{"Time": "07:30", "Venue": "V06-G09"}], "Th": [], "Fr": [{"Time": "09:30", "Venue": "V06-G09"}]}, {"subject": "PEFI411", "number": 422, "Mo": [], "Tu": [], "We": [{"Time": "13:00", "Venue": "V07-K01"}], "Th": [], "Fr": []}, {"subject": "PHIL112", "number": 423, "Mo": [], "Tu": [], "We": [], "Th": [{"Time": "11:00", "Venue": "V9A-G13"}], "Fr": []}, {"subject": "PHIL212", "number": 424, "Mo": [{"Time": "16:00", "Venue": "V25-G06"}], "Tu": [], "We": [{"Time": "13:00", "Venue": "V25-G06"}], "Th": [], "Fr": []}, {"subject": "PHIL311", "number": 425, "Mo": [], "Tu": [], "We": [{"Time": "14:30", "Venue": "Dept-1"}], "Th": [], "Fr": [{"Time": "11:00", "Venue": "Dept-1"}]}, {"subject": "PHIL312", "number": 426, "Mo": [], "Tu": [], "We": [{"Time": "14:30", "Venue": "Dept-4"}], "Th": [], "Fr": [{"Time": "11:00", "Venue": "Dept-4"}]}, {"subject": "PHSD411", "number": 427, "Mo": [], "Tu": [], "We": [{"Time": "07:30", "Venue": "V11-G07"}], "Th": [], "Fr": [{"Time": "09:30", "Venue": "V11-G07"}]}, {"subject": "PHSD512", "number": 428, "Mo": [{"Time": "09:30", "Venue": "V11-G06"}], "Tu": [], "We": [{"Time": "16:00", "Venue": "V11-G06"}], "Th": [], "Fr": []}, {"subject": "PHSE112", "number": 429, "Mo": [{"Time": "09:30", "Venue": "V11-G07"}], "Tu": [], "We": [{"Time": "14:30", "Venue": "V11-G07"}, {"Time": "16:00", "Venue": "V11-G07"}], "Th": [], "Fr": [{"Time": "11:00", "Venue": "V11-G07"}]}, {"subject": "PHSE212", "number": 430, "Mo": [{"Time": "07:30", "Venue": "V11-G06"}], "Tu": [{"Time": "13:00", "Venue": "V11-G06"}], "We": [], "Th": [{"Time": "14:30", "Venue": "V11-G06"}, {"Time": "16:00", "Venue": "V11-G06"}], "Fr": []}, {"subject": "PHSE312", "number": 431, "Mo": [{"Time": "14:30", "Venue": "V11-G07"}, {"Time": "16:00", "Venue": "V11-G07"}], "Tu": [], "We": [{"Time": "13:00", "Venue": "V11-G07"}], "Th": [{"Time": "07:30", "Venue": "V11-G07"}], "Fr": []}, {"subject": "PHSE412", "number": 432, "Mo": [{"Time": "14:30", "Venue": "V11-G06"}, {"Time": "16:00", "Venue": "V11-G06"}], "Tu": [], "We": [], "Th": [{"Time": "09:30", "Venue": "V11-G06"}], "Fr": [{"Time": "07:30", "Venue": "V11-G06"}]}, {"subject": "POLI112", "number": 433, "Mo": [], "Tu": [], "We": [{"Time": "07:30", "Venue": "V25-G08"}], "Th": [], "Fr": [{"Time": "09:30", "Venue": "V25-G08"}]}, {"subject": "POLI213", "number": 434, "Mo": [], "Tu": [], "We": [], "Th": [], "Fr": [{"Time": "07:30", "Venue": "V12-G01"}]}, {"subject": "POLI313", "number": 435, "Mo": [], "Tu": [], "We": [], "Th": [{"Time": "13:00", "Venue": "V12-G03"}], "Fr": [{"Time": "16:00", "Venue": "V12-G03"}]}, {"subject": "POLI314", "number": 436, "Mo": [{"Time": "16:00", "Venue": "V25-G03"}], "Tu": [], "We": [{"Time": "13:00", "Venue": "V25-G03"}], "Th": [], "Fr": []}, {"subject": "PSDT111E", "number": 437, "Mo": [], "Tu": [], "We": [{"Time": "14:30", "Venue": "V12-G05"}], "Th": [], "Fr": [{"Time": "11:00", "Venue": "V12-G05"}]}, {"subject": "PSDT111U", "number": 438, "Mo": [], "Tu": [], "We": [{"Time": "14:30", "Venue": "V12-G02"}], "Th": [], "Fr": [{"Time": "11:00", "Venue": "V12-G02"}]}, {"subject": "PSDT111a", "number": 439, "Mo": [], "Tu": [], "We": [{"Time": "07:30", "Venue": "V31-G02"}], "Th": [], "Fr": [{"Time": "09:30", "Venue": "V31-G02"}]}, {"subject": "PSYC111E", "number": 440, "Mo": [], "Tu": [], "We": [], "Th": [{"Time": "14:30", "Venue": "V25-G06"}], "Fr": []}, {"subject": "PSYC111U", "number": 441, "Mo": [{"Time": "09:30", "Venue": "V12-G02"}], "Tu": [], "We": [{"Time": "07:30", "Venue": "V12-G02"}], "Th": [], "Fr": []}, {"subject": "PSYC211", "number": 442, "Mo": [], "Tu": [], "We": [], "Th": [{"Time": "13:00", "Venue": "V12-G02"}], "Fr": []}, {"subject": "PSYC212", "number": 443, "Mo": [], "Tu": [{"Time": "09:30", "Venue": "V12-G02"}], "We": [], "Th": [], "Fr": []}, {"subject": "PSYC311B", "number": 444, "Mo": [], "Tu": [], "We": [], "Th": [{"Time": "07:30", "Venue": "V25-G08"}], "Fr": []}, {"subject": "PSYC311E", "number": 445, "Mo": [], "Tu": [], "We": [{"Time": "09:30", "Venue": "V25-G01"}], "Th": [], "Fr": []}, {"subject": "PSYC312B", "number": 446, "Mo": [], "Tu": [], "We": [{"Time": "11:00", "Venue": "V25-G03"}], "Th": [], "Fr": []}, {"subject": "PSYC312E", "number": 447, "Mo": [], "Tu": [{"Time": "07:30", "Venue": "V12-G05"}], "We": [], "Th": [], "Fr": []}, {"subject": "PUMA112", "number": 448, "Mo": [], "Tu": [], "We": [{"Time": "14:30", "Venue": "Dept-3"}], "Th": [], "Fr": [{"Time": "11:00", "Venue": "Dept-3"}]}, {"subject": "PUMA212", "number": 449, "Mo": [], "Tu": [], "We": [{"Time": "16:00", "Venue": "V06-G02"}], "Th": [], "Fr": []}, {"subject": "PUMA313", "number": 450, "Mo": [], "Tu": [], "We": [{"Time": "14:30", "Venue": "V9B-G02"}], "Th": [], "Fr": [{"Time": "11:00", "Venue": "V9B-G02"}]}, {"subject": "PUMA314", "number": 451, "Mo": [], "Tu": [], "We": [], "Th": [], "Fr": [{"Time": "14:30", "Venue": "V9C-G02"}]}, {"subject": "RESF411E", "number": 452, "Mo": [], "Tu": [], "We": [{"Time": "09:30", "Venue": "V12-G02"}], "Th": [], "Fr": []}, {"subject": "RESF411a", "number": 453, "Mo": [{"Time": "09:30", "Venue": "V11-G02"}], "Tu": [], "We": [], "Th": [], "Fr": []}, {"subject": "RESF412E", "number": 454, "Mo": [], "Tu": [], "We": [{"Time": "09:30", "Venue": "V12-G02"}], "Th": [], "Fr": []}, {"subject": "RESF412a", "number": 455, "Mo": [{"Time": "09:30", "Venue": "V11-G02"}], "Tu": [], "We": [], "Th": [], "Fr": []}, {"subject": "RESF511", "number": 456, "Mo": [], "Tu": [], "We": [], "Th": [{"Time": "13:00", "Venue": "V06-G06"}], "Fr": []}, {"subject": "SANL112", "number": 457, "Mo": [], "Tu": [], "We": [{"Time": "11:00", "Venue": "V07-K01"}], "Th": [], "Fr": []}, {"subject": "SANL213", "number": 458, "Mo": [], "Tu": [{"Time": "13:00", "Venue": "V06-G09"}], "We": [], "Th": [{"Time": "16:00", "Venue": "V06-G09"}], "Fr": []}, {"subject": "SANL315", "number": 459, "Mo": [], "Tu": [], "We": [], "Th": [], "Fr": [{"Time": "09:30", "Venue": "V9A-G13"}]}, {"subject": "SBUS111", "number": 460, "Mo": [], "Tu": [], "We": [], "Th": [{"Time": "11:00", "Venue": "V9A-G09"}], "Fr": []}, {"subject": "SBUS211", "number": 461, "Mo": [], "Tu": [], "We": [], "Th": [{"Time": "11:00", "Venue": "V9B-G02"}], "Fr": []}, {"subject": "SBUS212", "number": 462, "Mo": [], "Tu": [], "We": [], "Th": [], "Fr": [{"Time": "09:30", "Venue": "V9B-G01"}]}, {"subject": "SBUS311", "number": 463, "Mo": [], "Tu": [], "We": [], "Th": [{"Time": "11:00", "Venue": "V06-G06"}], "Fr": []}, {"subject": "SETM111", "number": 464, "Mo": [{"Time": "11:00", "Venue": "V06-G07"}], "Tu": [], "We": [{"Time": "09:30", "Venue": "V06-G07"}], "Th": [], "Fr": []}, {"subject": "SETM211", "number": 465, "Mo": [], "Tu": [], "We": [{"Time": "14:30", "Venue": "Dept-5"}], "Th": [], "Fr": [{"Time": "11:00", "Venue": "Dept-5"}]}, {"subject": "SOAF211", "number": 466, "Mo": [{"Time": "16:00", "Venue": "V06-G07"}], "Tu": [], "We": [], "Th": [], "Fr": []}, {"subject": "SOAF311", "number": 467, "Mo": [], "Tu": [], "We": [], "Th": [], "Fr": [{"Time": "11:00", "Venue": "V9A-G09"}]}, {"subject": "SOAF411", "number": 468, "Mo": [], "Tu": [], "We": [{"Time": "14:30", "Venue": "V25-G08"}], "Th": [], "Fr": []}, {"subject": "SOCY111E", "number": 469, "Mo": [], "Tu": [], "We": [], "Th": [{"Time": "13:00", "Venue": "V25-G01"}], "Fr": [{"Time": "16:00", "Venue": "V25-G01"}]}, {"subject": "SOCY111a", "number": 470, "Mo": [{"Time": "11:00", "Venue": "V07-110"}], "Tu": [], "We": [{"Time": "09:30", "Venue": "V07-110"}], "Th": [], "Fr": []}, {"subject": "SOCY211", "number": 471, "Mo": [{"Time": "07:30", "Venue": "V25-G01"}], "Tu": [], "We": [], "Th": [{"Time": "14:30", "Venue": "V25-G01"}], "Fr": []}, {"subject": "SOCY314", "number": 472, "Mo": [{"Time": "09:30", "Venue": "V9A-G07"}], "Tu": [], "We": [{"Time": "16:00", "Venue": "V9A-G07"}], "Th": [], "Fr": []}, {"subject": "SOCY315", "number": 473, "Mo": [], "Tu": [], "We": [{"Time": "07:30", "Venue": "V9B-G02"}], "Th": [], "Fr": [{"Time": "09:30", "Venue": "V9B-G02"}]}, {"subject": "SOFF111", "number": 474, "Mo": [], "Tu": [], "We": [], "Th": [{"Time": "07:30", "Venue": "V07-K01"}], "Fr": []}, {"subject": "SOFF211", "number": 475, "Mo": [{"Time": "09:30", "Venue": "V9A-G09"}], "Tu": [], "We": [{"Time": "16:00", "Venue": "V9A-G09"}], "Th": [], "Fr": []}, {"subject": "SOFF311", "number": 476, "Mo": [{"Time": "07:30", "Venue": "V25-G09"}], "Tu": [], "We": [], "Th": [{"Time": "14:30", "Venue": "V25-G09"}], "Fr": []}, {"subject": "SOFF411", "number": 477, "Mo": [], "Tu": [], "We": [], "Th": [{"Time": "09:30", "Venue": "V9A-G13"}], "Fr": []}, {"subject": "SOFI111", "number": 478, "Mo": [], "Tu": [], "We": [], "Th": [{"Time": "07:30", "Venue": "V9B-G01"}], "Fr": []}, {"subject": "SOFI211", "number": 479, "Mo": [], "Tu": [], "We": [], "Th": [], "Fr": [{"Time": "13:00", "Venue": "V07-206"}]}, {"subject": "SOFI311", "number": 480, "Mo": [], "Tu": [{"Time": "13:00", "Venue": "V06-G06"}], "We": [], "Th": [{"Time": "16:00", "Venue": "V06-G06"}], "Fr": []}, {"subject": "SOFI411", "number": 481, "Mo": [], "Tu": [], "We": [], "Th": [], "Fr": [{"Time": "14:30", "Venue": "V06-G08"}]}, {"subject": "SOFV111", "number": 482, "Mo": [{"Time": "11:00", "Venue": "V06-111"}], "Tu": [], "We": [{"Time": "09:30", "Venue": "V06-111"}], "Th": [], "Fr": []}, {"subject": "SOFV211", "number": 483, "Mo": [], "Tu": [{"Time": "09:30", "Venue": "V06-G06"}], "We": [{"Time": "11:00", "Venue": "V06-G06"}], "Th": [], "Fr": []}, {"subject": "SOFV311", "number": 484, "Mo": [], "Tu": [], "We": [{"Time": "07:30", "Venue": "V9A-G09"}], "Th": [], "Fr": [{"Time": "09:30", "Venue": "V9A-G09"}]}, {"subject": "SOFV411", "number": 485, "Mo": [], "Tu": [], "We": [], "Th": [{"Time": "13:00", "Venue": "V9A-G07"}], "Fr": [{"Time": "16:00", "Venue": "V9A-G07"}]}, {"subject": "SOIP211", "number": 486, "Mo": [], "Tu": [], "We": [], "Th": [], "Fr": [{"Time": "07:30", "Venue": "V9A-G09"}]}, {"subject": "SOIP311", "number": 487, "Mo": [], "Tu": [], "We": [], "Th": [{"Time": "07:30", "Venue": "V9C-G02"}], "Fr": []}, {"subject": "SOIP411", "number": 488, "Mo": [], "Tu": [], "We": [{"Time": "14:30", "Venue": "V06-G07"}], "Th": [], "Fr": [{"Time": "11:00", "Venue": "V06-G07"}]}, {"subject": "SPSO411E", "number": 489, "Mo": [{"Time": "16:00", "Venue": "V25-G01"}], "Tu": [], "We": [], "Th": [], "Fr": []}, {"subject": "SPSO411a", "number": 490, "Mo": [{"Time": "16:00", "Venue": "V06-G10"}], "Tu": [], "We": [], "Th": [], "Fr": []}, {"subject": "SSCE211", "number": 491, "Mo": [], "Tu": [], "We": [], "Th": [], "Fr": [{"Time": "16:00", "Venue": "V06-111"}]}, {"subject": "SSCE311", "number": 492, "Mo": [], "Tu": [{"Time": "11:00", "Venue": "V07-G04"}], "We": [], "Th": [], "Fr": []}, {"subject": "SSCE411", "number": 493, "Mo": [], "Tu": [], "We": [], "Th": [], "Fr": [{"Time": "13:00", "Venue": "V25-G03"}]}, {"subject": "SSCO111", "number": 494, "Mo": [], "Tu": [{"Time": "11:00", "Venue": "V31-G01"}], "We": [], "Th": [{"Time": "16:00", "Venue": "V31-G01"}], "Fr": []}, {"subject": "SSLL112", "number": 495, "Mo": [], "Tu": [], "We": [], "Th": [{"Time": "16:00", "Venue": "V31-G02"}], "Fr": []}, {"subject": "SSLL212", "number": 496, "Mo": [], "Tu": [], "We": [], "Th": [{"Time": "11:00", "Venue": "V25-G07"}], "Fr": []}, {"subject": "SSLL312", "number": 497, "Mo": [], "Tu": [{"Time": "11:00", "Venue": "V06-G09"}], "We": [], "Th": [], "Fr": [{"Time": "14:30", "Venue": "V06-G09"}]}, {"subject": "SSMD511", "number": 498, "Mo": [], "Tu": [], "We": [], "Th": [], "Fr": [{"Time": "11:00", "Venue": "Dept-4"}]}, {"subject": "SSSE112", "number": 499, "Mo": [], "Tu": [], "We": [{"Time": "07:30", "Venue": "V9A-G13"}], "Th": [], "Fr": []}, {"subject": "STFM111", "number": 500, "Mo": [], "Tu": [{"Time": "09:30", "Venue": "V9A-G20"}], "We": [{"Time": "11:00", "Venue": "V9A-G20"}], "Th": [], "Fr": []}, {"subject": "STFM212", "number": 501, "Mo": [], "Tu": [{"Time": "07:30", "Venue": "V9A-G07"}], "We": [], "Th": [], "Fr": [{"Time": "13:00", "Venue": "V9A-G07"}]}, {"subject": "STTF112", "number": 502, "Mo": [], "Tu": [{"Time": "07:30", "Venue": "V12-G03"}], "We": [], "Th": [], "Fr": [{"Time": "13:00", "Venue": "V12-G03"}]}, {"subject": "STTF115", "number": 503, "Mo": [], "Tu": [{"Time": "09:30", "Venue": "V9A-103"}], "We": [{"Time": "11:00", "Venue": "V9A-103"}], "Th": [], "Fr": []}, {"subject": "STTF215", "number": 504, "Mo": [], "Tu": [], "We": [], "Th": [], "Fr": [{"Time": "11:00", "Venue": "V9A-104"}]}, {"subject": "STTM211", "number": 505, "Mo": [], "Tu": [], "We": [], "Th": [], "Fr": [{"Time": "11:00", "Venue": "Dept-6"}]}, {"subject": "STTN111E", "number": 506, "Mo": [], "Tu": [], "We": [{"Time": "14:30", "Venue": "V06-G02"}], "Th": [], "Fr": [{"Time": "11:00", "Venue": "V06-G02"}]}, {"subject": "STTN111U", "number": 507, "Mo": [], "Tu": [], "We": [{"Time": "14:30", "Venue": "V11-G02"}], "Th": [], "Fr": [{"Time": "11:00", "Venue": "V11-G02"}]}, {"subject": "STTN115", "number": 508, "Mo": [], "Tu": [], "We": [{"Time": "14:30", "Venue": "V9A-103"}], "Th": [], "Fr": [{"Time": "14:30", "Venue": "V9A-103"}, {"Time": "16:00", "Venue": "V9A-103"}]}, {"subject": "STTN215", "number": 509, "Mo": [{"Time": "09:30", "Venue": "V9A-102"}], "Tu": [], "We": [{"Time": "14:30", "Venue": "V9A-102"}, {"Time": "16:00", "Venue": "V9A-102"}], "Th": [], "Fr": [{"Time": "11:00", "Venue": "V9A-102"}]}, {"subject": "STTN316", "number": 510, "Mo": [], "Tu": [], "We": [], "Th": [{"Time": "14:30", "Venue": "V9A-106"}], "Fr": []}, {"subject": "STTN317", "number": 511, "Mo": [], "Tu": [{"Time": "09:30", "Venue": "V9A-104"}], "We": [], "Th": [{"Time": "07:30", "Venue": "V9A-104"}], "Fr": []}, {"subject": "TAXC271", "number": 512, "Mo": [{"Time": "09:30", "Venue": "V9C-G02"}], "Tu": [], "We": [{"Time": "11:00", "Venue": "V9C-G02"}, {"Time": "13:00", "Venue": "V9C-G02"}], "Th": [], "Fr": []}, {"subject": "TAXC371", "number": 513, "Mo": [], "Tu": [{"Time": "09:30", "Venue": "V04-K03"}, {"Time": "11:00", "Venue": "V04-K03"}], "We": [], "Th": [{"Time": "09:30", "Venue": "V04-K03"}, {"Time": "11:00", "Venue": "V04-K03"}], "Fr": []}, {"subject": "TAXF211", "number": 514, "Mo": [{"Time": "13:00", "Venue": "V12-G04"}], "Tu": [{"Time": "14:30", "Venue": "V12-G04"}], "We": [{"Time": "09:30", "Venue": "V12-G04"}], "Th": [], "Fr": [{"Time": "11:00", "Venue": "V12-G04"}]}, {"subject": "TAXF371", "number": 515, "Mo": [{"Time": "11:00", "Venue": "V12-G04"}], "Tu": [{"Time": "07:30", "Venue": "V12-G04"}, {"Time": "09:30", "Venue": "V12-G04"}], "We": [], "Th": [], "Fr": [{"Time": "09:30", "Venue": "V12-G04"}]}, {"subject": "TECD411", "number": 516, "Mo": [{"Time": "07:30", "Venue": "V04-G03"}], "Tu": [], "We": [], "Th": [], "Fr": []}, {"subject": "VTEE313", "number": 517, "Mo": [], "Tu": [], "We": [{"Time": "16:00", "Venue": "V17-G11"}], "Th": [{"Time": "16:00", "Venue": "V17-G11"}], "Fr": [{"Time": "14:30", "Venue": "V17-G11"}]}, {"subject": "VTEE412", "number": 518, "Mo": [], "Tu": [], "We": [], "Th": [{"Time": "14:30", "Venue": "V17-G13"}], "Fr": []}, {"subject": "VTEE413", "number": 519, "Mo": [], "Tu": [], "We": [], "Th": [{"Time": "14:30", "Venue": "V17-G11"}], "Fr": []}, {"subject": "WISS111", "number": 520, "Mo": [], "Tu": [], "We": [], "Th": [], "Fr": [{"Time": "14:30", "Venue": "V9C-G01"}]}, {"subject": "WISS113", "number": 521, "Mo": [{"Time": "07:30", "Venue": "V07-G04"}], "Tu": [], "We": [], "Th": [{"Time": "14:30", "Venue": "V07-G04"}], "Fr": []}, {"subject": "WSKT213", "number": 522, "Mo": [], "Tu": [], "We": [{"Time": "09:30", "Venue": "V06-G09"}], "Th": [], "Fr": []}, {"subject": "WVES311E", "number": 523, "Mo": [], "Tu": [], "We": [{"Time": "11:00", "Venue": "V25-G01"}], "Th": [], "Fr": []}, {"subject": "WVES311U", "number": 524, "Mo": [], "Tu": [], "We": [], "Th": [{"Time": "11:00", "Venue": "V25-G08"}], "Fr": []}, {"subject": "WVLS313", "number": 525, "Mo": [], "Tu": [], "We": [], "Th": [{"Time": "16:00", "Venue": "V9B-G01"}], "Fr": []}, {"subject": "WVLS314", "number": 526, "Mo": [], "Tu": [], "We": [], "Th": [{"Time": "11:00", "Venue": "V12-G04"}], "Fr": []}, {"subject": "WVNS211E", "number": 527, "Mo": [], "Tu": [], "We": [], "Th": [{"Time": "11:00", "Venue": "V9A-106"}], "Fr": []}, {"subject": "WVNS211U", "number": 528, "Mo": [], "Tu": [], "We": [], "Th": [{"Time": "11:00", "Venue": "V03-103"}], "Fr": []}, {"subject": "WVOS312E", "number": 529, "Mo": [], "Tu": [], "We": [], "Th": [{"Time": "14:30", "Venue": "V12-G02"}], "Fr": []}, {"subject": "WVOS312U", "number": 530, "Mo": [{"Time": "13:00", "Venue": "V9B-G01"}], "Tu": [], "We": [], "Th": [], "Fr": []}, {"subject": "WVOS312a", "number": 531, "Mo": [], "Tu": [], "We": [], "Th": [{"Time": "13:00", "Venue": "V25-G07"}], "Fr": []}, {"subject": "WVRG311", "number": 532, "Mo": [{"Time": "14:30", "Venue": "V06-G10"}], "Tu": [], "We": [], "Th": [{"Time": "07:30", "Venue": "V06-G10"}], "Fr": []}, {"subject": "ZUAF211", "number": 533, "Mo": [{"Time": "16:00", "Venue": "V06-G09"}], "Tu": [], "We": [], "Th": [], "Fr": []}, {"subject": "ZUAF311", "number": 534, "Mo": [], "Tu": [], "We": [], "Th": [], "Fr": [{"Time": "11:00", "Venue": "V06-G08"}]}, {"subject": "ZUAF411", "number": 535, "Mo": [], "Tu": [], "We": [{"Time": "14:30", "Venue": "V06-111"}], "Th": [], "Fr": []}, {"subject": "ZUFF111", "number": 536, "Mo": [{"Time": "14:30", "Venue": "V06-111"}], "Tu": [], "We": [], "Th": [{"Time": "07:30", "Venue": "V06-111"}], "Fr": []}, {"subject": "ZUFF211", "number": 537, "Mo": [], "Tu": [{"Time": "07:30", "Venue": "V9A-G09"}], "We": [], "Th": [], "Fr": [{"Time": "13:00", "Venue": "V9A-G09"}]}, {"subject": "ZUFF311", "number": 538, "Mo": [], "Tu": [], "We": [], "Th": [], "Fr": [{"Time": "09:30", "Venue": "V06-G06"}]}, {"subject": "ZUFF411", "number": 539, "Mo": [], "Tu": [], "We": [], "Th": [], "Fr": [{"Time": "09:30", "Venue": "V07-K01"}]}, {"subject": "ZUFI111", "number": 540, "Mo": [], "Tu": [], "We": [], "Th": [{"Time": "07:30", "Venue": "V07-110"}], "Fr": []}, {"subject": "ZUFI211", "number": 541, "Mo": [], "Tu": [{"Time": "07:30", "Venue": "V07-K01"}], "We": [], "Th": [], "Fr": [{"Time": "13:00", "Venue": "V07-K01"}]}, {"subject": "ZUFI311", "number": 542, "Mo": [], "Tu": [], "We": [], "Th": [{"Time": "16:00", "Venue": "V25-G09"}], "Fr": []}, {"subject": "ZUFI411", "number": 543, "Mo": [], "Tu": [], "We": [], "Th": [{"Time": "07:30", "Venue": "V06-G06"}], "Fr": []}, {"subject": "ZUIP211", "number": 544, "Mo": [], "Tu": [], "We": [], "Th": [], "Fr": [{"Time": "07:30", "Venue": "V9C-G01"}]}, {"subject": "ZUIP311", "number": 545, "Mo": [], "Tu": [], "We": [], "Th": [{"Time": "07:30", "Venue": "V25-G09"}], "Fr": []}, {"subject": "ZUIP411", "number": 546, "Mo": [], "Tu": [{"Time": "16:00", "Venue": "V06-G09"}], "We": [], "Th": [{"Time": "09:30", "Venue": "V06-G09"}], "Fr": []}]